Workbook
Name ScenarioSelected: '01_Control'!$B$2
Name VolumeMethod: '01_Control'!$B$7
Name AssumptionTable: '02_Assumptions'!$A$1:$M$200
Name VOL_001_Derived: '05_Payroll_Activity'!$C$2:$G$2
Name AnnualSuccessfulTransactions: '05_Payroll_Activity'!$C$3:$G$3

Sheet 00_Read_Me
A1: Payroll Starter Financial Model
A2: Level 1 Controlled Placeholder Model
A4: Warning | B4: This workbook uses provisional management candidates and controlled placeholders. It is not an approved budget, forecast, provider quote, institutional commitment, contract, regulatory filing, investment representation, or factual operating result.
A5: Revenue warning | B5: Stakeholder revenue figures include internal transfers and are not additive. Consolidated External Revenue counts external inflows once.
A7: Canonical sources
A8: provisionalInputs | B8: docs/economics/offerings/rural-bank-payroll-starter/provisional-input-register-level-1.md
A9: level1Model | B9: docs/economics/offerings/rural-bank-payroll-starter/offering-economics-level-1.md
A10: summary | B10: docs/economics/offerings/rural-bank-payroll-starter/five-year-revenue-projection-summary.md
A11: specification | B11: docs/economics/offerings/rural-bank-payroll-starter/spreadsheet-financial-model.md
A13: Slice 2 sheets
A14: 00_Read_Me
A15: 01_Control
A16: 02_Assumptions
A17: 03_Assumption_Map
A18: 04_Adoption
A19: 05_Payroll_Activity
A20: 21_Checks

Sheet 01_Control
A1: Control | B1: Default | C1: Allowed values | D1: Notes
A2: Selected scenario | B2: Base | C2: Conservative, Base, Accelerated | D2: Data validation to be added in workbook implementation.
A3: Model start year | B3: Year 1 | C3: Year 1 | D3: Fixed for Level 1.
A4: Projection horizon | B4: 5 | C4: 5 | D4: Fixed for Level 1.
A5: Include optional SMS | B5: No | C5: Yes, No | D5: Core Payroll remains primary.
A6: Cost view | B6: Incremental Payroll | C6: Incremental Payroll, Full-Cost Stress Test | D6: Shared allocation deferred.
A7: Volume method | B7: Component-derived | C7: Component-derived | D7: Aggregate volume disabled until authorized.
A8: Discount rate | B8: Blocked | C8: Blocked | D8: Future FIN-001 needed.
A9: Model version | B9: Level 1 | C9: Level 1 | D9: Must match canonical documents.

Sheet 02_Assumptions
A1: Provisional Input ID | B1: Assumption ID or source | C1: Description | D1: Input Type | E1: Year | F1: Conservative | G1: Base | H1: Accelerated | I1: Selected Scenario Value | J1: Current Status | K1: Evidence Status | L1: Input Classification | M1: Source
A2: PI-L1-001 | B2: ADP-001 | C2: Newly onboarded banks during year | D2: yearVector | E2: Year 1 | F2: 2 | G2: 5 | H2: 10 | I2: =CHOOSE(MATCH('01_Control'!$B$2,$F$1:$H$1,0),F2,G2,H2) -> 5 | J2: Provisional | K2: Internal management candidate; not evidence-supported | L2: Controlled placeholder | M2: docs/economics/offerings/rural-bank-payroll-starter/provisional-input-register-level-1.md
A3: PI-L1-001 | B3: ADP-001 | C3: Newly onboarded banks during year | D3: yearVector | E3: Year 2 | F3: 3 | G3: 7 | H3: 12 | I3: =CHOOSE(MATCH('01_Control'!$B$2,$F$1:$H$1,0),F3,G3,H3) -> 7 | J3: Provisional | K3: Internal management candidate; not evidence-supported | L3: Controlled placeholder | M3: docs/economics/offerings/rural-bank-payroll-starter/provisional-input-register-level-1.md
A4: PI-L1-001 | B4: ADP-001 | C4: Newly onboarded banks during year | D4: yearVector | E4: Year 3 | F4: 4 | G4: 8 | H4: 15 | I4: =CHOOSE(MATCH('01_Control'!$B$2,$F$1:$H$1,0),F4,G4,H4) -> 8 | J4: Provisional | K4: Internal management candidate; not evidence-supported | L4: Controlled placeholder | M4: docs/economics/offerings/rural-bank-payroll-starter/provisional-input-register-level-1.md
A5: PI-L1-001 | B5: ADP-001 | C5: Newly onboarded banks during year | D5: yearVector | E5: Year 4 | F5: 4 | G5: 10 | H5: 18 | I5: =CHOOSE(MATCH('01_Control'!$B$2,$F$1:$H$1,0),F5,G5,H5) -> 10 | J5: Provisional | K5: Internal management candidate; not evidence-supported | L5: Controlled placeholder | M5: docs/economics/offerings/rural-bank-payroll-starter/provisional-input-register-level-1.md
A6: PI-L1-001 | B6: ADP-001 | C6: Newly onboarded banks during year | D6: yearVector | E6: Year 5 | F6: 5 | G6: 10 | H6: 20 | I6: =CHOOSE(MATCH('01_Control'!$B$2,$F$1:$H$1,0),F6,G6,H6) -> 10 | J6: Provisional | K6: Internal management candidate; not evidence-supported | L6: Controlled placeholder | M6: docs/economics/offerings/rural-bank-payroll-starter/provisional-input-register-level-1.md
A7: PI-L1-002 | B7: ADP-002 | C7: Active banks during year | D7: yearVector | E7: Year 1 | F7: 1 | G7: 3 | H7: 7 | I7: =CHOOSE(MATCH('01_Control'!$B$2,$F$1:$H$1,0),F7,G7,H7) -> 3 | J7: Provisional | K7: Internal management candidate; not evidence-supported | L7: Controlled placeholder | M7: docs/economics/offerings/rural-bank-payroll-starter/provisional-input-register-level-1.md
A8: PI-L1-002 | B8: ADP-002 | C8: Active banks during year | D8: yearVector | E8: Year 2 | F8: 3 | G8: 8 | H8: 16 | I8: =CHOOSE(MATCH('01_Control'!$B$2,$F$1:$H$1,0),F8,G8,H8) -> 8 | J8: Provisional | K8: Internal management candidate; not evidence-supported | L8: Controlled placeholder | M8: docs/economics/offerings/rural-bank-payroll-starter/provisional-input-register-level-1.md
A9: PI-L1-002 | B9: ADP-002 | C9: Active banks during year | D9: yearVector | E9: Year 3 | F9: 6 | G9: 14 | H9: 28 | I9: =CHOOSE(MATCH('01_Control'!$B$2,$F$1:$H$1,0),F9,G9,H9) -> 14 | J9: Provisional | K9: Internal management candidate; not evidence-supported | L9: Controlled placeholder | M9: docs/economics/offerings/rural-bank-payroll-starter/provisional-input-register-level-1.md
A10: PI-L1-002 | B10: ADP-002 | C10: Active banks during year | D10: yearVector | E10: Year 4 | F10: 9 | G10: 22 | H10: 42 | I10: =CHOOSE(MATCH('01_Control'!$B$2,$F$1:$H$1,0),F10,G10,H10) -> 22 | J10: Provisional | K10: Internal management candidate; not evidence-supported | L10: Controlled placeholder | M10: docs/economics/offerings/rural-bank-payroll-starter/provisional-input-register-level-1.md
A11: PI-L1-002 | B11: ADP-002 | C11: Active banks during year | D11: yearVector | E11: Year 5 | F11: 12 | G11: 32 | H11: 60 | I11: =CHOOSE(MATCH('01_Control'!$B$2,$F$1:$H$1,0),F11,G11,H11) -> 32 | J11: Provisional | K11: Internal management candidate; not evidence-supported | L11: Controlled placeholder | M11: docs/economics/offerings/rural-bank-payroll-starter/provisional-input-register-level-1.md
A12: PI-L1-003 | B12: ADP-003 | C12: Weighted average active months per active bank | D12: yearVector | E12: Year 1 | F12: 4 | G12: 5 | H12: 6 | I12: =CHOOSE(MATCH('01_Control'!$B$2,$F$1:$H$1,0),F12,G12,H12) -> 5 | J12: Provisional | K12: Internal management candidate; not evidence-supported | L12: Controlled placeholder | M12: docs/economics/offerings/rural-bank-payroll-starter/provisional-input-register-level-1.md
A13: PI-L1-003 | B13: ADP-003 | C13: Weighted average active months per active bank | D13: yearVector | E13: Year 2 | F13: 6 | G13: 7 | H13: 8 | I13: =CHOOSE(MATCH('01_Control'!$B$2,$F$1:$H$1,0),F13,G13,H13) -> 7 | J13: Provisional | K13: Internal management candidate; not evidence-supported | L13: Controlled placeholder | M13: docs/economics/offerings/rural-bank-payroll-starter/provisional-input-register-level-1.md
... A20: PI-L1-007 | B20: VOL-002 | C20: Successful completion rate | D20: scalar | E20: All | F20: 0.92 | G20: 0.96 | H20: 0.98 | I20: =CHOOSE(MATCH('01_Control'!$B$2,$F$1:$H$1,0),F20,G20,H20) -> 0.96 | J20: Provisional | K20: Internal management candidate; not evidence-supported | L20: Controlled placeholder | M20: docs/economics/offerings/rural-bank-payroll-starter/provisional-input-register-level-1.md
A21: PI-L1-008 | B21: VOL-001 | C21: Successful payroll transactions per active bank per month | D21: derived | E21: All | F21: CUS-001 x CUS-002 x CUS-003 x VOL-002 | G21: CUS-001 x CUS-002 x CUS-003 x VOL-002 | H21: CUS-001 x CUS-002 x CUS-003 x VOL-002 | I21: =CHOOSE(MATCH('01_Control'!$B$2,$F$1:$H$1,0),F21,G21,H21) -> CUS-001 x CUS-002 x CUS-003 x VOL-002 | J21: Derived | K21: Calculated from component assumptions | L21: Derived input | M21: docs/economics/offerings/rural-bank-payroll-starter/provisional-input-register-level-1.md
A22: PI-L1-009 | B22: EMP-001 | C22: Employer onboarding fee | D22: scalar | E22: All | F22: 1500 | G22: 3000 | H22: 5000 | I22: =CHOOSE(MATCH('01_Control'!$B$2,$F$1:$H$1,0),F22,G22,H22) -> 3000 | J22: Provisional | K22: Internal management candidate; not evidence-supported | L22: Controlled placeholder | M22: docs/economics/offerings/rural-bank-payroll-starter/provisional-input-register-level-1.md
A23: PI-L1-010 | B23: EMP-002 | C23: Employer monthly payroll-service fee | D23: scalar | E23: All | F23: 300 | G23: 750 | H23: 1250 | I23: =CHOOSE(MATCH('01_Control'!$B$2,$F$1:$H$1,0),F23,G23,H23) -> 750 | J23: Provisional | K23: Internal management candidate; not evidence-supported | L23: Controlled placeholder | M23: docs/economics/offerings/rural-bank-payroll-starter/provisional-input-register-level-1.md
A24: PI-L1-011 | B24: LIC-004 | C24: Rural-bank platform activation fee | D24: scalar | E24: All | F24: 50000 | G24: 50000 | H24: 50000 | I24: =CHOOSE(MATCH('01_Control'!$B$2,$F$1:$H$1,0),F24,G24,H24) -> 50000 | J24: Provisional | K24: Internal management candidate; not evidence-supported | L24: Controlled placeholder | M24: docs/economics/offerings/rural-bank-payroll-starter/provisional-input-register-level-1.md
A25: PI-L1-012 | B25: LIC-005 | C25: Annual platform subscription | D25: scalar | E25: All | F25: 60000 | G25: 60000 | H25: 60000 | I25: =CHOOSE(MATCH('01_Control'!$B$2,$F$1:$H$1,0),F25,G25,H25) -> 60000 | J25: Provisional | K25: Internal management candidate; not evidence-supported | L25: Controlled placeholder | M25: docs/economics/offerings/rural-bank-payroll-starter/provisional-input-register-level-1.md
A26: PI-L1-013 | B26: PRC-001 | C26: Fee per successful recipient disbursement | D26: scalar | E26: All | F26: 1 | G26: 1.5 | H26: 2 | I26: =CHOOSE(MATCH('01_Control'!$B$2,$F$1:$H$1,0),F26,G26,H26) -> 1.5 | J26: Provisional | K26: Internal management candidate; not evidence-supported | L26: Controlled placeholder | M26: docs/economics/offerings/rural-bank-payroll-starter/provisional-input-register-level-1.md
A27: PI-L1-014 | B27: RB-001 | C27: Rural-bank retained amount per successful recipient disbursement | D27: scalar | E27: All | F27: 0.4 | G27: 0.5 | H27: 0.6 | I27: =CHOOSE(MATCH('01_Control'!$B$2,$F$1:$H$1,0),F27,G27,H27) -> 0.5 | J27: Provisional | K27: Internal management candidate; not evidence-supported | L27: Controlled placeholder | M27: docs/economics/offerings/rural-bank-payroll-starter/provisional-input-register-level-1.md
A28: PI-L1-015 | B28: Decision 0003 | C28: EMP-001 split | D28: decision | E28: All | F28: ruralBank 40% / odti 60% | G28: ruralBank 40% / odti 60% | H28: ruralBank 40% / odti 60% | I28: =CHOOSE(MATCH('01_Control'!$B$2,$F$1:$H$1,0),F28,G28,H28) -> ruralBank 40% / odti 60% | J28: Provisional | K28: Internal management candidate; not evidence-supported | L28: Decision-backed provisional input | M28: docs/decisions/0003-payroll-starter-economic-treatment.md
A29: PI-L1-016 | B29: Decision 0003 | C29: EMP-002 split | D29: decision | E29: All | F29: ruralBank 60% / odti 40% | G29: ruralBank 60% / odti 40% | H29: ruralBank 60% / odti 40% | I29: =CHOOSE(MATCH('01_Control'!$B$2,$F$1:$H$1,0),F29,G29,H29) -> ruralBank 60% / odti 40% | J29: Provisional | K29: Internal management candidate; not evidence-supported | L29: Decision-backed provisional input | M29: docs/decisions/0003-payroll-starter-economic-treatment.md
A30: PI-L1-017 | B30: ODTI-001 | C30: Payroll-specific ODTI support cost per active bank-month | D30: scalar | E30: All | F30: 3000 | G30: 2500 | H30: 2000 | I30: =CHOOSE(MATCH('01_Control'!$B$2,$F$1:$H$1,0),F30,G30,H30) -> 2500 | J30: Provisional | K30: Internal management candidate; not evidence-supported | L30: Controlled placeholder | M30: docs/economics/offerings/rural-bank-payroll-starter/provisional-input-register-level-1.md
A31: PI-L1-018 | B31: ODTI-002 | C31: Payroll-specific ODTI implementation cost per newly onboarded bank | D31: scalar | E31: All | F31: 20000 | G31: 15000 | H31: 12000 | I31: =CHOOSE(MATCH('01_Control'!$B$2,$F$1:$H$1,0),F31,G31,H31) -> 15000 | J31: Provisional | K31: Internal management candidate; not evidence-supported | L31: Controlled placeholder | M31: docs/economics/offerings/rural-bank-payroll-starter/provisional-input-register-level-1.md
A32: PI-L1-019 | B32: OPS-001 | C32: DevOps setup fee per bank deployment | D32: scalar | E32: All | F32: 50000 | G32: 50000 | H32: 50000 | I32: =CHOOSE(MATCH('01_Control'!$B$2,$F$1:$H$1,0),F32,G32,H32) -> 50000 | J32: Provisional | K32: Internal management candidate; not evidence-supported | L32: Controlled placeholder | M32: docs/economics/offerings/rural-bank-payroll-starter/provisional-input-register-level-1.md
A33: PI-L1-020 | B33: OPS-002 | C33: DevOps monthly managed operations fee per active bank-month | D33: scalar | E33: All | F33: 10000 | G33: 10000 | H33: 10000 | I33: =CHOOSE(MATCH('01_Control'!$B$2,$F$1:$H$1,0),F33,G33,H33) -> 10000 | J33: Provisional | K33: Internal management candidate; not evidence-supported | L33: Controlled placeholder | M33: docs/economics/offerings/rural-bank-payroll-starter/provisional-input-register-level-1.md
A34: PI-L1-021 | B34: OPS-003 | C34: DevOps direct recurring cost per active bank-month | D34: scalar | E34: All | F34: 8000 | G34: 6000 | H34: 5000 | I34: =CHOOSE(MATCH('01_Control'!$B$2,$F$1:$H$1,0),F34,G34,H34) -> 6000 | J34: Provisional | K34: Internal management candidate; not evidence-supported | L34: Controlled placeholder | M34: docs/economics/offerings/rural-bank-payroll-starter/provisional-input-register-level-1.md
A35: PI-L1-022 | B35: CLD-001 | C35: Public-cloud cost per active bank-month | D35: scalar | E35: All | F35: 4000 | G35: 3000 | H35: 2500 | I35: =CHOOSE(MATCH('01_Control'!$B$2,$F$1:$H$1,0),F35,G35,H35) -> 3000 | J35: Provisional | K35: Internal management candidate; not evidence-supported | L35: Controlled placeholder | M35: docs/economics/offerings/rural-bank-payroll-starter/provisional-input-register-level-1.md
A36: PI-L1-023 | B36: RISK-002 | C36: Non-collection rate on employer commercial fees | D36: scalar | E36: All | F36: 0.05 | G36: 0.02 | H36: 0.01 | I36: =CHOOSE(MATCH('01_Control'!$B$2,$F$1:$H$1,0),F36,G36,H36) -> 0.02 | J36: Provisional | K36: Internal management candidate; not evidence-supported | L36: Controlled placeholder | M36: docs/economics/offerings/rural-bank-payroll-starter/provisional-input-register-level-1.md
A37: PI-L1-024 | B37: ATT-001 | C37: SMS attachment rate | D37: scalar | E37: All | F37: 0.25 | G37: 0.5 | H37: 0.7 | I37: =CHOOSE(MATCH('01_Control'!$B$2,$F$1:$H$1,0),F37,G37,H37) -> 0.5 | J37: Provisional | K37: Internal management candidate; not evidence-supported | L37: Controlled placeholder | M37: docs/economics/offerings/rural-bank-payroll-starter/provisional-input-register-level-1.md
A38: PI-L1-025 | B38: VAS-001 | C38: Customer-facing SMS price | D38: scalar | E38: All | F38: 1 | G38: 1 | H38: 1 | I38: =CHOOSE(MATCH('01_Control'!$B$2,$F$1:$H$1,0),F38,G38,H38) -> 1 | J38: Provisional | K38: Internal management candidate; not evidence-supported | L38: Controlled placeholder | M38: docs/economics/offerings/rural-bank-payroll-starter/provisional-input-register-level-1.md
A39: PI-L1-026 | B39: CST-001 | C39: SMS wholesale provider price | D39: scalar | E39: All | F39: 0.7 | G39: 0.5 | H39: 0.4 | I39: =CHOOSE(MATCH('01_Control'!$B$2,$F$1:$H$1,0),F39,G39,H39) -> 0.5 | J39: Provisional | K39: Internal management candidate; not evidence-supported | L39: Controlled placeholder | M39: docs/economics/offerings/rural-bank-payroll-starter/provisional-input-register-level-1.md
A40: PI-L1-027 | B40: SMS-001 | C40: SMS delivery success rate | D40: scalar | E40: All | F40: 0.9 | G40: 0.95 | H40: 0.97 | I40: =CHOOSE(MATCH('01_Control'!$B$2,$F$1:$H$1,0),F40,G40,H40) -> 0.95 | J40: Provisional | K40: Internal management candidate; not evidence-supported | L40: Controlled placeholder | M40: docs/economics/offerings/rural-bank-payroll-starter/provisional-input-register-level-1.md
A41: PI-L1-028 | B41: SMS-003 | C41: Failed-message treatment | D41: text | E41: All | F41: Delivered-only billing; failed attempts excluded | G41: Delivered-only billing; failed attempts excluded | H41: Delivered-only billing; failed attempts excluded | I41: =CHOOSE(MATCH('01_Control'!$B$2,$F$1:$H$1,0),F41,G41,H41) -> Delivered-only billing; failed attempts excluded | J41: Provisional | K41: Internal management candidate; not evidence-supported | L41: Governed policy input | M41: docs/economics/offerings/rural-bank-payroll-starter/provisional-input-register-level-1.md
A42: PI-L1-029 | B42: SMS-004 | C42: Privacy and consent readiness | D42: text | E42: All | F42: Internal modeling only; no external SMS use until privacy review | G42: Internal modeling only; no external SMS use until privacy review | H42: Internal modeling only; no external SMS use until privacy review | I42: =CHOOSE(MATCH('01_Control'!$B$2,$F$1:$H$1,0),F42,G42,H42) -> Internal modeling only; no external SMS use until privacy review | J42: Provisional | K42: Internal management candidate; not evidence-supported | L42: Governed policy input | M42: docs/economics/offerings/rural-bank-payroll-starter/provisional-input-register-level-1.md
A43: PI-L1-030 | B43: Decision 0003 | C43: SMS margin split | D43: text | E43: All | F43: Rural Bank retains gross SMS margin; ODTI markup is 0 | G43: Rural Bank retains gross SMS margin; ODTI markup is 0 | H43: Rural Bank retains gross SMS margin; ODTI markup is 0 | I43: =CHOOSE(MATCH('01_Control'!$B$2,$F$1:$H$1,0),F43,G43,H43) -> Rural Bank retains gross SMS margin; ODTI markup is 0 | J43: Provisional | K43: Internal management candidate; not evidence-supported | L43: Governed policy input | M43: docs/economics/offerings/rural-bank-payroll-starter/provisional-input-register-level-1.md
B44: TAX-001 | C44: Blocked. No tax-adjusted results are produced. | D44: blocked | E44: All | F44: Blocked | G44: Blocked | H44: Blocked | I44: Blocked | J44: Blocked | K44: Open | L44: Blocked or excluded | M44: docs/economics/offerings/rural-bank-payroll-starter/provisional-input-register-level-1.md
B45: ROY-001 | C45: Blocked. No 3neti royalty revenue or ODTI post-royalty contribution is produced. | D45: blocked | E45: All | F45: Blocked | G45: Blocked | H45: Blocked | I45: Blocked | J45: Blocked | K45: Open | L45: Blocked or excluded | M45: docs/economics/offerings/rural-bank-payroll-starter/provisional-input-register-level-1.md
B46: NET-001 | C46: Blocked. No NetBank fee-adjusted results are produced. | D46: blocked | E46: All | F46: Blocked | G46: Blocked | H46: Blocked | I46: Blocked | J46: Blocked | K46: Open | L46: Blocked or excluded | M46: docs/economics/offerings/rural-bank-payroll-starter/provisional-input-register-level-1.md
B47: NET-002 | C47: Blocked. No NetBank cost or contribution view is produced. | D47: blocked | E47: All | F47: Blocked | G47: Blocked | H47: Blocked | I47: Blocked | J47: Blocked | K47: Open | L47: Blocked or excluded | M47: docs/economics/offerings/rural-bank-payroll-starter/provisional-input-register-level-1.md
B48: PAR-001 | C48: Excluded. No business-development partner allocation is included. | D48: blocked | E48: All | F48: Blocked | G48: Blocked | H48: Blocked | I48: Blocked | J48: Blocked | K48: Open | L48: Blocked or excluded | M48: docs/economics/offerings/rural-bank-payroll-starter/provisional-input-register-level-1.md
B49: RB-002 | C49: Blocked. Rural Bank true incremental contribution after internal bank payroll-support cost is not produced. | D49: blocked | E49: All | F49: Blocked | G49: Blocked | H49: Blocked | I49: Blocked | J49: Blocked | K49: Open | L49: Blocked or excluded | M49: docs/economics/offerings/rural-bank-payroll-starter/provisional-input-register-level-1.md
B50: SMS-002 | C50: Excluded. SMS provider internal margin is not calculated. | D50: blocked | E50: All | F50: Blocked | G50: Blocked | H50: Blocked | I50: Blocked | J50: Blocked | K50: Open | L50: Blocked or excluded | M50: docs/economics/offerings/rural-bank-payroll-starter/provisional-input-register-level-1.md
B51: BAT-001 | C51: Deferred. No payroll batch fee is included. | D51: blocked | E51: All | F51: Blocked | G51: Blocked | H51: Blocked | I51: Blocked | J51: Blocked | K51: Open | L51: Blocked or excluded | M51: docs/economics/offerings/rural-bank-payroll-starter/provisional-input-register-level-1.md
B52: ALLOC-001 | C52: Deferred until shared platform allocation is mature enough to govern. | D52: blocked | E52: All | F52: Blocked | G52: Blocked | H52: Blocked | I52: Blocked | J52: Blocked | K52: Open | L52: Blocked or excluded | M52: docs/economics/offerings/rural-bank-payroll-starter/provisional-input-register-level-1.md
B53: ALLOC-002 | C53: Deferred until shared platform allocation is mature enough to govern. | D53: blocked | E53: All | F53: Blocked | G53: Blocked | H53: Blocked | I53: Blocked | J53: Blocked | K53: Open | L53: Blocked or excluded | M53: docs/economics/offerings/rural-bank-payroll-starter/provisional-input-register-level-1.md
B54: PLT-001 | C54: Deferred until shared platform allocation is mature enough to govern. | D54: blocked | E54: All | F54: Blocked | G54: Blocked | H54: Blocked | I54: Blocked | J54: Blocked | K54: Open | L54: Blocked or excluded | M54: docs/economics/offerings/rural-bank-payroll-starter/provisional-input-register-level-1.md

Sheet 03_Assumption_Map
A1: Assumption ID | B1: Used By | C1: Formula / Role | D1: Output Tabs | E1: Status
A2: CUS-001 | B2: VOL-001; Active employers | C2: Component input | D2: 04_Adoption; 05_Payroll_Activity | E2: Provisional
A3: CUS-002 | B3: VOL-001 | C3: Component input | D3: 05_Payroll_Activity | E3: Provisional
A4: CUS-003 | B4: VOL-001 | C4: Component input | D4: 05_Payroll_Activity | E4: Provisional
A5: VOL-002 | B5: VOL-001 | C5: Component input | D5: 05_Payroll_Activity | E5: Provisional
A6: VOL-001 | B6: Annual successful payroll transactions | C6: Derived input only | D6: 05_Payroll_Activity | E6: Derived
A7: ADP-001 | B7: Cumulative banks; newly onboarded employer relationships | C7: Primitive input | D7: 04_Adoption | E7: Provisional
A8: ADP-002 | B8: Annual successful payroll transactions; active employers | C8: Primitive input | D8: 04_Adoption; 05_Payroll_Activity | E8: Provisional
A9: ADP-003 | B9: Annual successful payroll transactions | C9: Primitive input | D9: 04_Adoption; 05_Payroll_Activity | E9: Provisional
A10: ATT-001 | B10: SMS-attached delivered transactions | C10: Optional SMS input | D10: 05_Payroll_Activity; 13_SMS_Variant | E10: Provisional
A11: SMS-001 | B11: SMS-attached delivered transactions | C11: Optional SMS input | D11: 05_Payroll_Activity; 13_SMS_Variant | E11: Provisional
A12: RB-002 | B12: Rural Bank true contribution | C12: Blocked input | D12: 10_Rural_Bank_View; 21_Checks | E12: Blocked
... A15: NET-001 | B15: NetBank fee-adjusted result | C15: Blocked input | D15: 14_Consolidated_View; 21_Checks | E15: Blocked

Sheet 04_Adoption
A1: Scenario | B1: Metric | C1: Year 1 | D1: Year 2 | E1: Year 3 | F1: Year 4 | G1: Year 5
A2: Conservative | B2: Newly onboarded banks | C2: ='02_Assumptions'!$F$2 -> 2 | D2: ='02_Assumptions'!$F$3 -> 3 | E2: ='02_Assumptions'!$F$4 -> 4 | F2: ='02_Assumptions'!$F$5 -> 4 | G2: ='02_Assumptions'!$F$6 -> 5
A3: Conservative | B3: Cumulative onboarded banks | C3: =SUM('02_Assumptions'!$F$2) -> 2 | D3: =SUM('02_Assumptions'!$F$2,'02_Assumptions'!$F$3) -> 5 | E3: =SUM('02_Assumptions'!$F$2,'02_Assumptions'!$F$3,'02_Assumptions'!$F$4) -> 9 | F3: =SUM('02_Assumptions'!$F$2,'02_Assumptions'!$F$3,'02_Assumptions'!$F$4,'02_Assumptions'!$F$5) -> 13 | G3: =SUM('02_Assumptions'!$F$2,'02_Assumptions'!$F$3,'02_Assumptions'!$F$4,'02_Assumptions'!$F$5,'02_Assumptions'!$F$6) -> 18
A4: Conservative | B4: Active banks | C4: ='02_Assumptions'!$F$7 -> 1 | D4: ='02_Assumptions'!$F$8 -> 3 | E4: ='02_Assumptions'!$F$9 -> 6 | F4: ='02_Assumptions'!$F$10 -> 9 | G4: ='02_Assumptions'!$F$11 -> 12
A5: Conservative | B5: Weighted average active months | C5: ='02_Assumptions'!$F$12 -> 4 | D5: ='02_Assumptions'!$F$13 -> 6 | E5: ='02_Assumptions'!$F$14 -> 7 | F5: ='02_Assumptions'!$F$15 -> 8 | G5: ='02_Assumptions'!$F$16 -> 8
A6: Conservative | B6: Active employers | C6: ='02_Assumptions'!$F$7*'02_Assumptions'!$F$17 -> 2 | D6: ='02_Assumptions'!$F$8*'02_Assumptions'!$F$17 -> 6 | E6: ='02_Assumptions'!$F$9*'02_Assumptions'!$F$17 -> 12 | F6: ='02_Assumptions'!$F$10*'02_Assumptions'!$F$17 -> 18 | G6: ='02_Assumptions'!$F$11*'02_Assumptions'!$F$17 -> 24
A7: Conservative | B7: Newly onboarded employer relationships | C7: ='02_Assumptions'!$F$2*'02_Assumptions'!$F$17 -> 4 | D7: ='02_Assumptions'!$F$3*'02_Assumptions'!$F$17 -> 6 | E7: ='02_Assumptions'!$F$4*'02_Assumptions'!$F$17 -> 8 | F7: ='02_Assumptions'!$F$5*'02_Assumptions'!$F$17 -> 8 | G7: ='02_Assumptions'!$F$6*'02_Assumptions'!$F$17 -> 10
A8: Base | B8: Newly onboarded banks | C8: ='02_Assumptions'!$G$2 -> 5 | D8: ='02_Assumptions'!$G$3 -> 7 | E8: ='02_Assumptions'!$G$4 -> 8 | F8: ='02_Assumptions'!$G$5 -> 10 | G8: ='02_Assumptions'!$G$6 -> 10
A9: Base | B9: Cumulative onboarded banks | C9: =SUM('02_Assumptions'!$G$2) -> 5 | D9: =SUM('02_Assumptions'!$G$2,'02_Assumptions'!$G$3) -> 12 | E9: =SUM('02_Assumptions'!$G$2,'02_Assumptions'!$G$3,'02_Assumptions'!$G$4) -> 20 | F9: =SUM('02_Assumptions'!$G$2,'02_Assumptions'!$G$3,'02_Assumptions'!$G$4,'02_Assumptions'!$G$5) -> 30 | G9: =SUM('02_Assumptions'!$G$2,'02_Assumptions'!$G$3,'02_Assumptions'!$G$4,'02_Assumptions'!$G$5,'02_Assumptions'!$G$6) -> 40
A10: Base | B10: Active banks | C10: ='02_Assumptions'!$G$7 -> 3 | D10: ='02_Assumptions'!$G$8 -> 8 | E10: ='02_Assumptions'!$G$9 -> 14 | F10: ='02_Assumptions'!$G$10 -> 22 | G10: ='02_Assumptions'!$G$11 -> 32
A11: Base | B11: Weighted average active months | C11: ='02_Assumptions'!$G$12 -> 5 | D11: ='02_Assumptions'!$G$13 -> 7 | E11: ='02_Assumptions'!$G$14 -> 8 | F11: ='02_Assumptions'!$G$15 -> 9 | G11: ='02_Assumptions'!$G$16 -> 10
A12: Base | B12: Active employers | C12: ='02_Assumptions'!$G$7*'02_Assumptions'!$G$17 -> 12 | D12: ='02_Assumptions'!$G$8*'02_Assumptions'!$G$17 -> 32 | E12: ='02_Assumptions'!$G$9*'02_Assumptions'!$G$17 -> 56 | F12: ='02_Assumptions'!$G$10*'02_Assumptions'!$G$17 -> 88 | G12: ='02_Assumptions'!$G$11*'02_Assumptions'!$G$17 -> 128
A13: Base | B13: Newly onboarded employer relationships | C13: ='02_Assumptions'!$G$2*'02_Assumptions'!$G$17 -> 20 | D13: ='02_Assumptions'!$G$3*'02_Assumptions'!$G$17 -> 28 | E13: ='02_Assumptions'!$G$4*'02_Assumptions'!$G$17 -> 32 | F13: ='02_Assumptions'!$G$5*'02_Assumptions'!$G$17 -> 40 | G13: ='02_Assumptions'!$G$6*'02_Assumptions'!$G$17 -> 40
A14: Accelerated | B14: Newly onboarded banks | C14: ='02_Assumptions'!$H$2 -> 10 | D14: ='02_Assumptions'!$H$3 -> 12 | E14: ='02_Assumptions'!$H$4 -> 15 | F14: ='02_Assumptions'!$H$5 -> 18 | G14: ='02_Assumptions'!$H$6 -> 20
A15: Accelerated | B15: Cumulative onboarded banks | C15: =SUM('02_Assumptions'!$H$2) -> 10 | D15: =SUM('02_Assumptions'!$H$2,'02_Assumptions'!$H$3) -> 22 | E15: =SUM('02_Assumptions'!$H$2,'02_Assumptions'!$H$3,'02_Assumptions'!$H$4) -> 37 | F15: =SUM('02_Assumptions'!$H$2,'02_Assumptions'!$H$3,'02_Assumptions'!$H$4,'02_Assumptions'!$H$5) -> 55 | G15: =SUM('02_Assumptions'!$H$2,'02_Assumptions'!$H$3,'02_Assumptions'!$H$4,'02_Assumptions'!$H$5,'02_Assumptions'!$H$6) -> 75
A16: Accelerated | B16: Active banks | C16: ='02_Assumptions'!$H$7 -> 7 | D16: ='02_Assumptions'!$H$8 -> 16 | E16: ='02_Assumptions'!$H$9 -> 28 | F16: ='02_Assumptions'!$H$10 -> 42 | G16: ='02_Assumptions'!$H$11 -> 60
A17: Accelerated | B17: Weighted average active months | C17: ='02_Assumptions'!$H$12 -> 6 | D17: ='02_Assumptions'!$H$13 -> 8 | E17: ='02_Assumptions'!$H$14 -> 9 | F17: ='02_Assumptions'!$H$15 -> 10 | G17: ='02_Assumptions'!$H$16 -> 10
A18: Accelerated | B18: Active employers | C18: ='02_Assumptions'!$H$7*'02_Assumptions'!$H$17 -> 42 | D18: ='02_Assumptions'!$H$8*'02_Assumptions'!$H$17 -> 96 | E18: ='02_Assumptions'!$H$9*'02_Assumptions'!$H$17 -> 168 | F18: ='02_Assumptions'!$H$10*'02_Assumptions'!$H$17 -> 252 | G18: ='02_Assumptions'!$H$11*'02_Assumptions'!$H$17 -> 360
A19: Accelerated | B19: Newly onboarded employer relationships | C19: ='02_Assumptions'!$H$2*'02_Assumptions'!$H$17 -> 60 | D19: ='02_Assumptions'!$H$3*'02_Assumptions'!$H$17 -> 72 | E19: ='02_Assumptions'!$H$4*'02_Assumptions'!$H$17 -> 90 | F19: ='02_Assumptions'!$H$5*'02_Assumptions'!$H$17 -> 108 | G19: ='02_Assumptions'!$H$6*'02_Assumptions'!$H$17 -> 120

Sheet 05_Payroll_Activity
A1: Scenario | B1: Metric | C1: Year 1 | D1: Year 2 | E1: Year 3 | F1: Year 4 | G1: Year 5
A2: Conservative | B2: Derived VOL-001 | C2: ='02_Assumptions'!$F$17*'02_Assumptions'!$F$18*'02_Assumptions'!$F$19*'02_Assumptions'!$F$20 -> 36.8 | D2: ='02_Assumptions'!$F$17*'02_Assumptions'!$F$18*'02_Assumptions'!$F$19*'02_Assumptions'!$F$20 -> 36.8 | E2: ='02_Assumptions'!$F$17*'02_Assumptions'!$F$18*'02_Assumptions'!$F$19*'02_Assumptions'!$F$20 -> 36.8 | F2: ='02_Assumptions'!$F$17*'02_Assumptions'!$F$18*'02_Assumptions'!$F$19*'02_Assumptions'!$F$20 -> 36.8 | G2: ='02_Assumptions'!$F$17*'02_Assumptions'!$F$18*'02_Assumptions'!$F$19*'02_Assumptions'!$F$20 -> 36.8
A3: Conservative | B3: Annual successful payroll transactions | C3: ='02_Assumptions'!$F$7*'02_Assumptions'!$F$12*('02_Assumptions'!$F$17*'02_Assumptions'!$F$18*'02_Assumptions'!$F$19*'02_Assumptions'!$F$20) -> 147.2 | D3: ='02_Assumptions'!$F$8*'02_Assumptions'!$F$13*('02_Assumptions'!$F$17*'02_Assumptions'!$F$18*'02_Assumptions'!$F$19*'02_Assumptions'!$F$20) -> 662.4 | E3: ='02_Assumptions'!$F$9*'02_Assumptions'!$F$14*('02_Assumptions'!$F$17*'02_Assumptions'!$F$18*'02_Assumptions'!$F$19*'02_Assumptions'!$F$20) -> 1545.6 | F3: ='02_Assumptions'!$F$10*'02_Assumptions'!$F$15*('02_Assumptions'!$F$17*'02_Assumptions'!$F$18*'02_Assumptions'!$F$19*'02_Assumptions'!$F$20) -> 2649.6 | G3: ='02_Assumptions'!$F$11*'02_Assumptions'!$F$16*('02_Assumptions'!$F$17*'02_Assumptions'!$F$18*'02_Assumptions'!$F$19*'02_Assumptions'!$F$20) -> 3532.8
A4: Conservative | B4: SMS-attached delivered transactions | C4: =147.20000000000002*'02_Assumptions'!$F$37*'02_Assumptions'!$F$40 -> 33.12 | D4: =662.4000000000001*'02_Assumptions'!$F$37*'02_Assumptions'!$F$40 -> 149.04 | E4: =1545.6000000000001*'02_Assumptions'!$F$37*'02_Assumptions'!$F$40 -> 347.76 | F4: =2649.6000000000004*'02_Assumptions'!$F$37*'02_Assumptions'!$F$40 -> 596.16 | G4: =3532.8*'02_Assumptions'!$F$37*'02_Assumptions'!$F$40 -> 794.88
A5: Base | B5: Derived VOL-001 | C5: ='02_Assumptions'!$G$17*'02_Assumptions'!$G$18*'02_Assumptions'!$G$19*'02_Assumptions'!$G$20 -> 268.8 | D5: ='02_Assumptions'!$G$17*'02_Assumptions'!$G$18*'02_Assumptions'!$G$19*'02_Assumptions'!$G$20 -> 268.8 | E5: ='02_Assumptions'!$G$17*'02_Assumptions'!$G$18*'02_Assumptions'!$G$19*'02_Assumptions'!$G$20 -> 268.8 | F5: ='02_Assumptions'!$G$17*'02_Assumptions'!$G$18*'02_Assumptions'!$G$19*'02_Assumptions'!$G$20 -> 268.8 | G5: ='02_Assumptions'!$G$17*'02_Assumptions'!$G$18*'02_Assumptions'!$G$19*'02_Assumptions'!$G$20 -> 268.8
A6: Base | B6: Annual successful payroll transactions | C6: ='02_Assumptions'!$G$7*'02_Assumptions'!$G$12*('02_Assumptions'!$G$17*'02_Assumptions'!$G$18*'02_Assumptions'!$G$19*'02_Assumptions'!$G$20) -> 4032 | D6: ='02_Assumptions'!$G$8*'02_Assumptions'!$G$13*('02_Assumptions'!$G$17*'02_Assumptions'!$G$18*'02_Assumptions'!$G$19*'02_Assumptions'!$G$20) -> 15052.8 | E6: ='02_Assumptions'!$G$9*'02_Assumptions'!$G$14*('02_Assumptions'!$G$17*'02_Assumptions'!$G$18*'02_Assumptions'!$G$19*'02_Assumptions'!$G$20) -> 30105.6 | F6: ='02_Assumptions'!$G$10*'02_Assumptions'!$G$15*('02_Assumptions'!$G$17*'02_Assumptions'!$G$18*'02_Assumptions'!$G$19*'02_Assumptions'!$G$20) -> 53222.4 | G6: ='02_Assumptions'!$G$11*'02_Assumptions'!$G$16*('02_Assumptions'!$G$17*'02_Assumptions'!$G$18*'02_Assumptions'!$G$19*'02_Assumptions'!$G$20) -> 86016
A7: Base | B7: SMS-attached delivered transactions | C7: =4032*'02_Assumptions'!$G$37*'02_Assumptions'!$G$40 -> 1915.2 | D7: =15052.800000000001*'02_Assumptions'!$G$37*'02_Assumptions'!$G$40 -> 7150.08 | E7: =30105.600000000002*'02_Assumptions'!$G$37*'02_Assumptions'!$G$40 -> 14300.16 | F7: =53222.4*'02_Assumptions'!$G$37*'02_Assumptions'!$G$40 -> 25280.64 | G7: =86016*'02_Assumptions'!$G$37*'02_Assumptions'!$G$40 -> 40857.6
A8: Accelerated | B8: Derived VOL-001 | C8: ='02_Assumptions'!$H$17*'02_Assumptions'!$H$18*'02_Assumptions'!$H$19*'02_Assumptions'!$H$20 -> 705.6 | D8: ='02_Assumptions'!$H$17*'02_Assumptions'!$H$18*'02_Assumptions'!$H$19*'02_Assumptions'!$H$20 -> 705.6 | E8: ='02_Assumptions'!$H$17*'02_Assumptions'!$H$18*'02_Assumptions'!$H$19*'02_Assumptions'!$H$20 -> 705.6 | F8: ='02_Assumptions'!$H$17*'02_Assumptions'!$H$18*'02_Assumptions'!$H$19*'02_Assumptions'!$H$20 -> 705.6 | G8: ='02_Assumptions'!$H$17*'02_Assumptions'!$H$18*'02_Assumptions'!$H$19*'02_Assumptions'!$H$20 -> 705.6
A9: Accelerated | B9: Annual successful payroll transactions | C9: ='02_Assumptions'!$H$7*'02_Assumptions'!$H$12*('02_Assumptions'!$H$17*'02_Assumptions'!$H$18*'02_Assumptions'!$H$19*'02_Assumptions'!$H$20) -> 29635.2 | D9: ='02_Assumptions'!$H$8*'02_Assumptions'!$H$13*('02_Assumptions'!$H$17*'02_Assumptions'!$H$18*'02_Assumptions'!$H$19*'02_Assumptions'!$H$20) -> 90316.8 | E9: ='02_Assumptions'!$H$9*'02_Assumptions'!$H$14*('02_Assumptions'!$H$17*'02_Assumptions'!$H$18*'02_Assumptions'!$H$19*'02_Assumptions'!$H$20) -> 177811.2 | F9: ='02_Assumptions'!$H$10*'02_Assumptions'!$H$15*('02_Assumptions'!$H$17*'02_Assumptions'!$H$18*'02_Assumptions'!$H$19*'02_Assumptions'!$H$20) -> 296352 | G9: ='02_Assumptions'!$H$11*'02_Assumptions'!$H$16*('02_Assumptions'!$H$17*'02_Assumptions'!$H$18*'02_Assumptions'!$H$19*'02_Assumptions'!$H$20) -> 423360
A10: Accelerated | B10: SMS-attached delivered transactions | C10: =29635.2*'02_Assumptions'!$H$37*'02_Assumptions'!$H$40 -> 20122.301 | D10: =90316.8*'02_Assumptions'!$H$37*'02_Assumptions'!$H$40 -> 61325.107 | E10: =177811.2*'02_Assumptions'!$H$37*'02_Assumptions'!$H$40 -> 120733.8 | F10: =296352*'02_Assumptions'!$H$37*'02_Assumptions'!$H$40 -> 201223.01 | G10: =423360*'02_Assumptions'!$H$37*'02_Assumptions'!$H$40 -> 287461.44

Sheet 21_Checks
A1: Check | B1: Actual | C1: Expected | D1: Difference | E1: Status | F1: Notes
A2: Active banks <= cumulative onboarded banks | B2: All scenarios | C2: True | D2: 0 | E2: OK | F2: Validated by scaffold and formulas.
A3: Weighted active months between 0 and 12 | B3: All scenarios | C3: 0 to 12 | D3: 0 | E3: OK | F3: Validated by scaffold and formulas.
A4: Active employers reconcile | B4: All scenarios | C4: ADP-002 x CUS-001 | D4: 0 | E4: OK | F4: Formula-backed on 04_Adoption.
A5: Newly onboarded employer relationships reconcile | B5: All scenarios | C5: ADP-001 x CUS-001 | D5: 0 | E5: OK | F5: Formula-backed on 04_Adoption.
A6: VOL-001 equals component-derived formula | B6: All scenarios | C6: CUS-001 x CUS-002 x CUS-003 x VOL-002 | D6: 0 | E6: OK | F6: Formula-backed on 05_Payroll_Activity.
A7: No independent VOL-001 input in component-derived mode | B7: Component-derived | C7: Component-derived | D7: 0 | E7: OK | F7: VOL-001 is displayed as derived only.
A8: Annual successful transactions match canonical model | B8: All scenarios | C8: Canonical Level 1 values | D8: 0 | E8: OK | F8: Formula results match canonical activity table.
A9: RB-001 <= PRC-001 | B9: All scenarios | C9: True | D9: 0 | E9: OK | F9: Rural Bank retention cannot exceed recipient fee.
A10: Blocked assumptions visibly blocked | B10: 11 rows | C10: Visible | D10: 0 | E10: OK | F10: Blocked rows appear on 02_Assumptions.
A11: NPV cash-flow linkage | B11: Unavailable | C11: Blocked | E11: Blocked | F11: Capital-budgeting prerequisites not yet implemented.
A12: IRR sign pattern | B12: Unavailable | C12: Blocked | E12: Blocked | F12: Capital-budgeting prerequisites not yet implemented.
A13: RB-001 <= PRC-001 | B13: All scenarios | C13: True | D13: 0 | E13: OK | F13: Pricing split remains valid.
A14: EMP-001 split sums to 100% | B14: All scenarios | C14: 100% | D14: 0 | E14: OK | F14: Decision 0003 split rows.
A15: EMP-002 split sums to 100% | B15: All scenarios | C15: 100% | D15: 0 | E15: OK | F15: Decision 0003 split rows.
A16: External revenue counts employer fees once | B16: All scenarios | C16: True | D16: 0 | E16: OK | F16: Core external revenue is separated from entity revenue.
A17: Stakeholder revenue is non-additive | B17: All scenarios | C17: Warning visible | D17: 0 | E17: OK | F17: Entity revenue rows remain non-additive.
A18: Core Payroll excludes SMS | B18: All scenarios | C18: True | D18: 0 | E18: OK | F18: SMS appears only in 13_SMS_Variant and optional consolidated rows.
A19: SMS margin formula | B19: Collected revenue less wholesale cost | C19: True | D19: 0 | E19: OK | F19: Wholesale provider cost is not reduced by non-collection.
A20: ODTI qualifiers | B20: Pre-tax/pre-royalty/NetBank-fee-blocked | C20: Visible | D20: 0 | E20: OK | F20: Blocked qualifiers preserved.
A21: Blocked exclusions | B21: TAX-001; ROY-001; NET-001 | C21: Blocked | E21: Blocked | F21: Final net results remain unavailable.
A22: Payroll funding excluded from cost of sales | B22: Pass-through only | C22: Excluded | D22: 0 | E22: OK | F22: No payroll funding appears as revenue or cost of sales.
A23: SMS wholesale cost remains unreduced | B23: 13_SMS_Variant wholesale row | C23: Visible | D23: 0 | E23: OK | F23: Wholesale provider cost is separate from non-collection.
A24: Incremental and modernization costs separate | B24: 09_Operating_Expenses | C24: Separate rows | D24: 0 | E24: OK | F24: Shared modernization cost is not merged into incremental Payroll contribution.
A25: CLD-001 remains outside DevOps | B25: Public-cloud modernization cost | C25: Rural Bank external outflow | D25: 0 | E25: OK | F25: Cloud remains outside DevOps contribution.
A26: RB-002 remains blocked | B26: Rural Bank true net contribution | C26: Blocked | E26: Blocked | F26: Internal bank support cost has no authorized value.
A27: TAX-001 remains blocked | B27: Tax-adjusted net income | C27: Blocked | E27: Blocked | F27: No tax-adjusted result is produced.
A28: ROY-001 remains blocked | B28: Post-royalty ODTI contribution | C28: Blocked | E28: Blocked | F28: No 3neti royalty adjustment is included.
A29: NET-001 remains blocked | B29: NetBank fee-adjusted results | C29: Blocked | E29: Blocked | F29: No NetBank fee basis is approved.
A30: Management P&L is not GAAP/PFRS | B30: 15_Profit_and_Loss | C30: Qualified | D30: 0 | E30: OK | F30: Formal accounting presentation remains blocked.
A31: Revenue is not assumed to equal cash receipt | B31: 16_Cash_Flow | C31: COL-001 blocked | E31: Blocked | F31: Cash timing remains unresolved.
A32: Ending cash remains blocked | B32: 16_Cash_Flow | C32: Blocked | E32: Blocked | F32: Beginning cash and financing assumptions are unavailable.
A33: NPV and IRR remain outside Slice 4 | B33: 17_Capital_Budgeting | C33: Future slice | E33: Blocked | F33: Capital budgeting remains Slice 5.
A34: NPV uses cash flows only | B34: No NPV calculated | C34: Blocked | E34: Blocked | F34: FIN-001 and cash-flow prerequisites are unavailable.
A35: IRR sign pattern valid | B35: No IRR calculated | C35: Blocked | E35: Blocked | F35: No governed investment cash-flow series exists.
A36: Discount rate assumption exists | B36: FIN-001 missing | C36: Blocked | E36: Blocked | F36: Future assumptions-register update required.
A37: Sensitivity targets link to model outputs | B37: 18_Sensitivity | C37: Linked | D37: 0 | E37: OK | F37: Formula targets reference workbook outputs.
A38: No pasted valuation outputs | B38: 17_Capital_Budgeting | C38: Blocked rows | D38: 0 | E38: OK | F38: NPV and IRR are not hardcoded or forced.
A39: Rural Bank NPV blocked | B39: RB-002; cash timing; FIN-001 | C39: Blocked | E39: Blocked | F39: True Rural Bank cash flow remains unavailable.
A40: ODTI NPV blocked | B40: Tax; royalty; NetBank; cash timing | C40: Blocked | E40: Blocked | F40: Final ODTI cash flow remains unavailable.
A41: Discount-rate sensitivity blocked | B41: FIN-001 missing | C41: Blocked | E41: Blocked | F41: No discount-rate matrix is produced.
A42: Scenario comparison consumes model outputs | B42: 19_Scenarios | C42: Linked | D42: 0 | E42: OK | F42: Scenario table references existing workbook sheets.
A43: Dashboard uses linked outputs | B43: 20_Dashboard | C43: Linked | D43: 0 | E43: OK | F43: Dashboard rows reference model outputs and controls.
A44: Dashboard ERROR count surfaced | B44: 20_Dashboard | C44: Visible | D44: 0 | E44: OK | F44: ERROR count links to 21_Checks.
A45: Warnings remain visible | B45: 00_Read_Me; 20_Dashboard | C45: Visible | D45: 0 | E45: OK | F45: Workbook warning remains on Read Me; dashboard preserves blocked metrics.
A46: Source lineage covers required categories | B46: 15 | C46: 15 | D46: 0 | E46: OK | F46: 22_Source_Lineage maps the primary model areas.
A47: No workbook-as-source-of-truth lineage | B47: 22_Source_Lineage | C47: Repository documents | D47: 0 | E47: OK | F47: Lineage points to canonical documents and assumptions.
A48: NPV and IRR remain blocked | B48: 17_Capital_Budgeting | C48: Blocked | E48: Blocked | F48: No discount-rate or cash-flow authorization exists.
A49: Stakeholder revenue remains non-additive | B49: 07_Revenue warning | C49: Non-additive | D49: 0 | E49: OK | F49: Consolidated external revenue remains separate.
A50: Core Payroll and SMS remain separated | B50: 13_SMS_Variant optional | C50: Separated | D50: 0 | E50: OK | F50: Dashboard and scenarios keep SMS optional.
A51: Model status | B51: No ERROR rows | C51: OK | D51: 0 | E51: OK | F51: Blocked rows are known limitations, not validation errors.

Sheet 06_Pricing
A1: Scenario | B1: Pricing item | C1: Value | D1: Source | E1: Notes
A2: Conservative | B2: EMP-001 Employer onboarding fee | C2: ='02_Assumptions'!$F$22 -> 1500 | D2: EMP-001 / provisional input | E2: Customer-facing employer onboarding price.
A3: Conservative | B3: EMP-001 Rural Bank share | C3: 0.4 | D3: Decision 0003 / PI-L1-015 | E3: Decision-backed provisional split.
A4: Conservative | B4: EMP-001 ODTI share | C4: 0.6 | D4: Decision 0003 / PI-L1-015 | E4: Decision-backed provisional split.
A5: Conservative | B5: EMP-002 Employer monthly payroll-service fee | C5: ='02_Assumptions'!$F$23 -> 300 | D5: EMP-002 / provisional input | E5: Customer-facing recurring employer fee.
A6: Conservative | B6: EMP-002 Rural Bank share | C6: 0.6 | D6: Decision 0003 / PI-L1-016 | E6: Decision-backed provisional split.
A7: Conservative | B7: EMP-002 ODTI share | C7: 0.4 | D7: Decision 0003 / PI-L1-016 | E7: Decision-backed provisional split.
A8: Conservative | B8: PRC-001 Recipient disbursement fee | C8: ='02_Assumptions'!$F$26 -> 1 | D8: PRC-001 / provisional input | E8: Customer-facing recipient disbursement fee.
A9: Conservative | B9: RB-001 Rural Bank retained transaction amount | C9: ='02_Assumptions'!$F$27 -> 0.4 | D9: RB-001 / provisional input | E9: Must not exceed PRC-001.
A10: Conservative | B10: ODTI recipient transaction amount | C10: ='06_Pricing'!$C$8-'06_Pricing'!$C$9 -> 0.6 | D10: PRC-001 less RB-001 | E10: Derived transaction-platform amount.
A11: Conservative | B11: LIC-004 Activation fee | C11: ='02_Assumptions'!$F$24 -> 50000 | D11: LIC-004 / provisional input | E11: Rural-bank platform access activation.
A12: Conservative | B12: LIC-005 Annual platform subscription | C12: ='02_Assumptions'!$F$25 -> 60000 | D12: LIC-005 / provisional input | E12: Annual subscription; monthly recognition uses active bank-months divided by 12.
A13: Conservative | B13: RISK-002 Collection loss rate | C13: ='02_Assumptions'!$F$36 -> 0.05 | D13: RISK-002 / provisional input | E13: Applies to eligible employer commercial fees.
A14: Conservative | B14: VAS-001 SMS customer-facing price | C14: ='02_Assumptions'!$F$38 -> 1 | D14: VAS-001 / provisional input | E14: Optional SMS price.
A15: Conservative | B15: CST-001 SMS wholesale provider price | C15: ='02_Assumptions'!$F$39 -> 0.7 | D15: CST-001 / provisional input | E15: Wholesale provider cost remains payable under baseline.
A16: Base | B16: EMP-001 Employer onboarding fee | C16: ='02_Assumptions'!$G$22 -> 3000 | D16: EMP-001 / provisional input | E16: Customer-facing employer onboarding price.
A17: Base | B17: EMP-001 Rural Bank share | C17: 0.4 | D17: Decision 0003 / PI-L1-015 | E17: Decision-backed provisional split.
A18: Base | B18: EMP-001 ODTI share | C18: 0.6 | D18: Decision 0003 / PI-L1-015 | E18: Decision-backed provisional split.
A19: Base | B19: EMP-002 Employer monthly payroll-service fee | C19: ='02_Assumptions'!$G$23 -> 750 | D19: EMP-002 / provisional input | E19: Customer-facing recurring employer fee.
A20: Base | B20: EMP-002 Rural Bank share | C20: 0.6 | D20: Decision 0003 / PI-L1-016 | E20: Decision-backed provisional split.
A21: Base | B21: EMP-002 ODTI share | C21: 0.4 | D21: Decision 0003 / PI-L1-016 | E21: Decision-backed provisional split.
A22: Base | B22: PRC-001 Recipient disbursement fee | C22: ='02_Assumptions'!$G$26 -> 1.5 | D22: PRC-001 / provisional input | E22: Customer-facing recipient disbursement fee.
A23: Base | B23: RB-001 Rural Bank retained transaction amount | C23: ='02_Assumptions'!$G$27 -> 0.5 | D23: RB-001 / provisional input | E23: Must not exceed PRC-001.
A24: Base | B24: ODTI recipient transaction amount | C24: ='06_Pricing'!$C$22-'06_Pricing'!$C$23 -> 1 | D24: PRC-001 less RB-001 | E24: Derived transaction-platform amount.
A25: Base | B25: LIC-004 Activation fee | C25: ='02_Assumptions'!$G$24 -> 50000 | D25: LIC-004 / provisional input | E25: Rural-bank platform access activation.
A26: Base | B26: LIC-005 Annual platform subscription | C26: ='02_Assumptions'!$G$25 -> 60000 | D26: LIC-005 / provisional input | E26: Annual subscription; monthly recognition uses active bank-months divided by 12.
A27: Base | B27: RISK-002 Collection loss rate | C27: ='02_Assumptions'!$G$36 -> 0.02 | D27: RISK-002 / provisional input | E27: Applies to eligible employer commercial fees.
A28: Base | B28: VAS-001 SMS customer-facing price | C28: ='02_Assumptions'!$G$38 -> 1 | D28: VAS-001 / provisional input | E28: Optional SMS price.
A29: Base | B29: CST-001 SMS wholesale provider price | C29: ='02_Assumptions'!$G$39 -> 0.5 | D29: CST-001 / provisional input | E29: Wholesale provider cost remains payable under baseline.
A30: Accelerated | B30: EMP-001 Employer onboarding fee | C30: ='02_Assumptions'!$H$22 -> 5000 | D30: EMP-001 / provisional input | E30: Customer-facing employer onboarding price.
A31: Accelerated | B31: EMP-001 Rural Bank share | C31: 0.4 | D31: Decision 0003 / PI-L1-015 | E31: Decision-backed provisional split.
A32: Accelerated | B32: EMP-001 ODTI share | C32: 0.6 | D32: Decision 0003 / PI-L1-015 | E32: Decision-backed provisional split.
A33: Accelerated | B33: EMP-002 Employer monthly payroll-service fee | C33: ='02_Assumptions'!$H$23 -> 1250 | D33: EMP-002 / provisional input | E33: Customer-facing recurring employer fee.
A34: Accelerated | B34: EMP-002 Rural Bank share | C34: 0.6 | D34: Decision 0003 / PI-L1-016 | E34: Decision-backed provisional split.
A35: Accelerated | B35: EMP-002 ODTI share | C35: 0.4 | D35: Decision 0003 / PI-L1-016 | E35: Decision-backed provisional split.
A36: Accelerated | B36: PRC-001 Recipient disbursement fee | C36: ='02_Assumptions'!$H$26 -> 2 | D36: PRC-001 / provisional input | E36: Customer-facing recipient disbursement fee.
A37: Accelerated | B37: RB-001 Rural Bank retained transaction amount | C37: ='02_Assumptions'!$H$27 -> 0.6 | D37: RB-001 / provisional input | E37: Must not exceed PRC-001.
A38: Accelerated | B38: ODTI recipient transaction amount | C38: ='06_Pricing'!$C$36-'06_Pricing'!$C$37 -> 1.4 | D38: PRC-001 less RB-001 | E38: Derived transaction-platform amount.
A39: Accelerated | B39: LIC-004 Activation fee | C39: ='02_Assumptions'!$H$24 -> 50000 | D39: LIC-004 / provisional input | E39: Rural-bank platform access activation.
A40: Accelerated | B40: LIC-005 Annual platform subscription | C40: ='02_Assumptions'!$H$25 -> 60000 | D40: LIC-005 / provisional input | E40: Annual subscription; monthly recognition uses active bank-months divided by 12.
A41: Accelerated | B41: RISK-002 Collection loss rate | C41: ='02_Assumptions'!$H$36 -> 0.01 | D41: RISK-002 / provisional input | E41: Applies to eligible employer commercial fees.
A42: Accelerated | B42: VAS-001 SMS customer-facing price | C42: ='02_Assumptions'!$H$38 -> 1 | D42: VAS-001 / provisional input | E42: Optional SMS price.
A43: Accelerated | B43: CST-001 SMS wholesale provider price | C43: ='02_Assumptions'!$H$39 -> 0.4 | D43: CST-001 / provisional input | E43: Wholesale provider cost remains payable under baseline.

Sheet 07_Revenue
A1: Scenario | B1: Metric | C1: Year 1 | D1: Year 2 | E1: Year 3 | F1: Year 4 | G1: Year 5
A2: Conservative | B2: Employer onboarding revenue | C2: ='04_Adoption'!$C$7*'06_Pricing'!$C$2 -> 6000 | D2: ='04_Adoption'!$D$7*'06_Pricing'!$C$2 -> 9000 | E2: ='04_Adoption'!$E$7*'06_Pricing'!$C$2 -> 12000 | F2: ='04_Adoption'!$F$7*'06_Pricing'!$C$2 -> 12000 | G2: ='04_Adoption'!$G$7*'06_Pricing'!$C$2 -> 15000
A3: Conservative | B3: Employer monthly service revenue | C3: ='04_Adoption'!$C$6*'04_Adoption'!$C$5*'06_Pricing'!$C$5 -> 2400 | D3: ='04_Adoption'!$D$6*'04_Adoption'!$D$5*'06_Pricing'!$C$5 -> 10800 | E3: ='04_Adoption'!$E$6*'04_Adoption'!$E$5*'06_Pricing'!$C$5 -> 25200 | F3: ='04_Adoption'!$F$6*'04_Adoption'!$F$5*'06_Pricing'!$C$5 -> 43200 | G3: ='04_Adoption'!$G$6*'04_Adoption'!$G$5*'06_Pricing'!$C$5 -> 57600
A4: Conservative | B4: Recipient disbursement fee revenue | C4: ='05_Payroll_Activity'!$C$3*'06_Pricing'!$C$8 -> 147.2 | D4: ='05_Payroll_Activity'!$D$3*'06_Pricing'!$C$8 -> 662.4 | E4: ='05_Payroll_Activity'!$E$3*'06_Pricing'!$C$8 -> 1545.6 | F4: ='05_Payroll_Activity'!$F$3*'06_Pricing'!$C$8 -> 2649.6 | G4: ='05_Payroll_Activity'!$G$3*'06_Pricing'!$C$8 -> 3532.8
A5: Conservative | B5: Core external revenue | C5: =('04_Adoption'!$C$7*'06_Pricing'!$C$2)+('04_Adoption'!$C$6*'04_Adoption'!$C$5*'06_Pricing'!$C$5)+('05_Payroll_Activity'!$C$3*'06_Pricing'!$C$8) -> 8547.2 | D5: =('04_Adoption'!$D$7*'06_Pricing'!$C$2)+('04_Adoption'!$D$6*'04_Adoption'!$D$5*'06_Pricing'!$C$5)+('05_Payroll_Activity'!$D$3*'06_Pricing'!$C$8) -> 20462.4 | E5: =('04_Adoption'!$E$7*'06_Pricing'!$C$2)+('04_Adoption'!$E$6*'04_Adoption'!$E$5*'06_Pricing'!$C$5)+('05_Payroll_Activity'!$E$3*'06_Pricing'!$C$8) -> 38745.6 | F5: =('04_Adoption'!$F$7*'06_Pricing'!$C$2)+('04_Adoption'!$F$6*'04_Adoption'!$F$5*'06_Pricing'!$C$5)+('05_Payroll_Activity'!$F$3*'06_Pricing'!$C$8) -> 57849.6 | G5: =('04_Adoption'!$G$7*'06_Pricing'!$C$2)+('04_Adoption'!$G$6*'04_Adoption'!$G$5*'06_Pricing'!$C$5)+('05_Payroll_Activity'!$G$3*'06_Pricing'!$C$8) -> 76132.8
A6: Conservative | B6: Rural Bank entity revenue - non-additive | C6: ='10_Rural_Bank_View'!$C$2 -> 3703.94 | D6: ='10_Rural_Bank_View'!$D$2 -> 9827.71 | E6: ='10_Rural_Bank_View'!$E$2 -> 19511.33 | F6: ='10_Rural_Bank_View'!$F$2 -> 30190.85 | G6: ='10_Rural_Bank_View'!$G$2 -> 39874.46
A7: Conservative | B7: ODTI entity revenue - non-additive | C7: ='11_ODTI_View'!$C$2 -> 124415.9 | D7: ='11_ODTI_View'!$D$2 -> 249611.57 | E7: ='11_ODTI_View'!$E$2 -> 427296.99 | F7: ='11_ODTI_View'!$F$2 -> 584766.27 | G7: ='11_ODTI_View'!$G$2 -> 762451.7
A8: Conservative | B8: DevOps entity revenue - non-additive | C8: ='12_DevOps_View'!$C$2 -> 140000 | D8: ='12_DevOps_View'!$D$2 -> 330000 | E8: ='12_DevOps_View'!$E$2 -> 620000 | F8: ='12_DevOps_View'!$F$2 -> 920000 | G8: ='12_DevOps_View'!$G$2 -> 1210000
A9: Base | B9: Employer onboarding revenue | C9: ='04_Adoption'!$C$13*'06_Pricing'!$C$16 -> 60000 | D9: ='04_Adoption'!$D$13*'06_Pricing'!$C$16 -> 84000 | E9: ='04_Adoption'!$E$13*'06_Pricing'!$C$16 -> 96000 | F9: ='04_Adoption'!$F$13*'06_Pricing'!$C$16 -> 120000 | G9: ='04_Adoption'!$G$13*'06_Pricing'!$C$16 -> 120000
A10: Base | B10: Employer monthly service revenue | C10: ='04_Adoption'!$C$12*'04_Adoption'!$C$11*'06_Pricing'!$C$19 -> 45000 | D10: ='04_Adoption'!$D$12*'04_Adoption'!$D$11*'06_Pricing'!$C$19 -> 168000 | E10: ='04_Adoption'!$E$12*'04_Adoption'!$E$11*'06_Pricing'!$C$19 -> 336000 | F10: ='04_Adoption'!$F$12*'04_Adoption'!$F$11*'06_Pricing'!$C$19 -> 594000 | G10: ='04_Adoption'!$G$12*'04_Adoption'!$G$11*'06_Pricing'!$C$19 -> 960000
A11: Base | B11: Recipient disbursement fee revenue | C11: ='05_Payroll_Activity'!$C$6*'06_Pricing'!$C$22 -> 6048 | D11: ='05_Payroll_Activity'!$D$6*'06_Pricing'!$C$22 -> 22579.2 | E11: ='05_Payroll_Activity'!$E$6*'06_Pricing'!$C$22 -> 45158.4 | F11: ='05_Payroll_Activity'!$F$6*'06_Pricing'!$C$22 -> 79833.6 | G11: ='05_Payroll_Activity'!$G$6*'06_Pricing'!$C$22 -> 129024
A12: Base | B12: Core external revenue | C12: =('04_Adoption'!$C$13*'06_Pricing'!$C$16)+('04_Adoption'!$C$12*'04_Adoption'!$C$11*'06_Pricing'!$C$19)+('05_Payroll_Activity'!$C$6*'06_Pricing'!$C$22) -> 111048 | D12: =('04_Adoption'!$D$13*'06_Pricing'!$C$16)+('04_Adoption'!$D$12*'04_Adoption'!$D$11*'06_Pricing'!$C$19)+('05_Payroll_Activity'!$D$6*'06_Pricing'!$C$22) -> 274579.2 | E12: =('04_Adoption'!$E$13*'06_Pricing'!$C$16)+('04_Adoption'!$E$12*'04_Adoption'!$E$11*'06_Pricing'!$C$19)+('05_Payroll_Activity'!$E$6*'06_Pricing'!$C$22) -> 477158.4 | F12: =('04_Adoption'!$F$13*'06_Pricing'!$C$16)+('04_Adoption'!$F$12*'04_Adoption'!$F$11*'06_Pricing'!$C$19)+('05_Payroll_Activity'!$F$6*'06_Pricing'!$C$22) -> 793833.6 | G12: =('04_Adoption'!$G$13*'06_Pricing'!$C$16)+('04_Adoption'!$G$12*'04_Adoption'!$G$11*'06_Pricing'!$C$19)+('05_Payroll_Activity'!$G$6*'06_Pricing'!$C$22) -> 1209024
A13: Base | B13: Rural Bank entity revenue - non-additive | C13: ='10_Rural_Bank_View'!$C$5 -> 51955.68 | D13: ='10_Rural_Bank_View'!$D$5 -> 139087.87 | E13: ='10_Rural_Bank_View'!$E$5 -> 249951.74 | F13: ='10_Rural_Bank_View'!$F$5 -> 422390.98 | G13: ='10_Rural_Bank_View'!$G$5 -> 653667.84
A14: Base | B14: ODTI entity revenue - non-additive | C14: ='11_ODTI_View'!$C$5 -> 381871.36 | D14: ='11_ODTI_View'!$D$5 -> 759999.74 | E14: ='11_ODTI_View'!$E$5 -> 1177663.5 | F14: ='11_ODTI_View'!$F$5 -> 1845565.9 | G14: ='11_ODTI_View'!$G$5 -> 2631175.7
A15: Base | B15: DevOps entity revenue - non-additive | C15: ='12_DevOps_View'!$C$4 -> 400000 | D15: ='12_DevOps_View'!$D$4 -> 910000 | E15: ='12_DevOps_View'!$E$4 -> 1520000 | F15: ='12_DevOps_View'!$F$4 -> 2480000 | G15: ='12_DevOps_View'!$G$4 -> 3700000
A16: Accelerated | B16: Employer onboarding revenue | C16: ='04_Adoption'!$C$19*'06_Pricing'!$C$30 -> 300000 | D16: ='04_Adoption'!$D$19*'06_Pricing'!$C$30 -> 360000 | E16: ='04_Adoption'!$E$19*'06_Pricing'!$C$30 -> 450000 | F16: ='04_Adoption'!$F$19*'06_Pricing'!$C$30 -> 540000 | G16: ='04_Adoption'!$G$19*'06_Pricing'!$C$30 -> 600000
A17: Accelerated | B17: Employer monthly service revenue | C17: ='04_Adoption'!$C$18*'04_Adoption'!$C$17*'06_Pricing'!$C$33 -> 315000 | D17: ='04_Adoption'!$D$18*'04_Adoption'!$D$17*'06_Pricing'!$C$33 -> 960000 | E17: ='04_Adoption'!$E$18*'04_Adoption'!$E$17*'06_Pricing'!$C$33 -> 1890000 | F17: ='04_Adoption'!$F$18*'04_Adoption'!$F$17*'06_Pricing'!$C$33 -> 3150000 | G17: ='04_Adoption'!$G$18*'04_Adoption'!$G$17*'06_Pricing'!$C$33 -> 4500000
A18: Accelerated | B18: Recipient disbursement fee revenue | C18: ='05_Payroll_Activity'!$C$9*'06_Pricing'!$C$36 -> 59270.4 | D18: ='05_Payroll_Activity'!$D$9*'06_Pricing'!$C$36 -> 180633.6 | E18: ='05_Payroll_Activity'!$E$9*'06_Pricing'!$C$36 -> 355622.4 | F18: ='05_Payroll_Activity'!$F$9*'06_Pricing'!$C$36 -> 592704 | G18: ='05_Payroll_Activity'!$G$9*'06_Pricing'!$C$36 -> 846720
A19: Accelerated | B19: Core external revenue | C19: =('04_Adoption'!$C$19*'06_Pricing'!$C$30)+('04_Adoption'!$C$18*'04_Adoption'!$C$17*'06_Pricing'!$C$33)+('05_Payroll_Activity'!$C$9*'06_Pricing'!$C$36) -> 674270.4 | D19: =('04_Adoption'!$D$19*'06_Pricing'!$C$30)+('04_Adoption'!$D$18*'04_Adoption'!$D$17*'06_Pricing'!$C$33)+('05_Payroll_Activity'!$D$9*'06_Pricing'!$C$36) -> 1500633.6 | E19: =('04_Adoption'!$E$19*'06_Pricing'!$C$30)+('04_Adoption'!$E$18*'04_Adoption'!$E$17*'06_Pricing'!$C$33)+('05_Payroll_Activity'!$E$9*'06_Pricing'!$C$36) -> 2695622.4 | F19: =('04_Adoption'!$F$19*'06_Pricing'!$C$30)+('04_Adoption'!$F$18*'04_Adoption'!$F$17*'06_Pricing'!$C$33)+('05_Payroll_Activity'!$F$9*'06_Pricing'!$C$36) -> 4282704 | G19: =('04_Adoption'!$G$19*'06_Pricing'!$C$30)+('04_Adoption'!$G$18*'04_Adoption'!$G$17*'06_Pricing'!$C$33)+('05_Payroll_Activity'!$G$9*'06_Pricing'!$C$36) -> 5946720
A20: Accelerated | B20: Rural Bank entity revenue - non-additive | C20: ='10_Rural_Bank_View'!$C$8 -> 323513.31 | D20: ='10_Rural_Bank_View'!$D$8 -> 766448.18 | E20: ='10_Rural_Bank_View'!$E$8 -> 1406479.9 | F20: ='10_Rural_Bank_View'!$F$8 -> 2260973.1 | G20: ='10_Rural_Bank_View'!$G$8 -> 3162075.8
A21: Accelerated | B21: ODTI entity revenue - non-additive | C21: ='11_ODTI_View'!$C$8 -> 1054014.4 | D21: ='11_ODTI_View'!$D$8 -> 1959179.1 | E21: ='11_ODTI_View'!$E$8 -> 3272186.3 | F21: ='11_ODTI_View'!$F$8 -> 4978903.9 | G21: ='11_ODTI_View'!$G$8 -> 6725177
A22: Accelerated | B22: DevOps entity revenue - non-additive | C22: ='12_DevOps_View'!$C$6 -> 920000 | D22: ='12_DevOps_View'!$D$6 -> 1880000 | E22: ='12_DevOps_View'!$E$6 -> 3270000 | F22: ='12_DevOps_View'!$F$6 -> 5100000 | G22: ='12_DevOps_View'!$G$6 -> 7000000

Sheet 10_Rural_Bank_View
A1: Scenario | B1: Metric | C1: Year 1 | D1: Year 2 | E1: Year 3 | F1: Year 4 | G1: Year 5
A2: Conservative | B2: Rural Bank core revenue | C2: =(('04_Adoption'!$C$7*'06_Pricing'!$C$2)*'06_Pricing'!$C$3+('04_Adoption'!$C$6*'04_Adoption'!$C$5*'06_Pricing'!$C$5)*'06_Pricing'!$C$6+'05_Payroll_Activity'!$C$3*'06_Pricing'!$C$9)*(1-'06_Pricing'!$C$13) -> 3703.94 | D2: =(('04_Adoption'!$D$7*'06_Pricing'!$C$2)*'06_Pricing'!$C$3+('04_Adoption'!$D$6*'04_Adoption'!$D$5*'06_Pricing'!$C$5)*'06_Pricing'!$C$6+'05_Payroll_Activity'!$D$3*'06_Pricing'!$C$9)*(1-'06_Pricing'!$C$13) -> 9827.71 | E2: =(('04_Adoption'!$E$7*'06_Pricing'!$C$2)*'06_Pricing'!$C$3+('04_Adoption'!$E$6*'04_Adoption'!$E$5*'06_Pricing'!$C$5)*'06_Pricing'!$C$6+'05_Payroll_Activity'!$E$3*'06_Pricing'!$C$9)*(1-'06_Pricing'!$C$13) -> 19511.33 | F2: =(('04_Adoption'!$F$7*'06_Pricing'!$C$2)*'06_Pricing'!$C$3+('04_Adoption'!$F$6*'04_Adoption'!$F$5*'06_Pricing'!$C$5)*'06_Pricing'!$C$6+'05_Payroll_Activity'!$F$3*'06_Pricing'!$C$9)*(1-'06_Pricing'!$C$13) -> 30190.85 | G2: =(('04_Adoption'!$G$7*'06_Pricing'!$C$2)*'06_Pricing'!$C$3+('04_Adoption'!$G$6*'04_Adoption'!$G$5*'06_Pricing'!$C$5)*'06_Pricing'!$C$6+'05_Payroll_Activity'!$G$3*'06_Pricing'!$C$9)*(1-'06_Pricing'!$C$13) -> 39874.46
A3: Conservative | B3: Rural Bank SMS margin | C3: ='13_SMS_Variant'!$C$5 -> 8.28 | D3: ='13_SMS_Variant'!$D$5 -> 37.26 | E3: ='13_SMS_Variant'!$E$5 -> 86.94 | F3: ='13_SMS_Variant'!$F$5 -> 149.04 | G3: ='13_SMS_Variant'!$G$5 -> 198.72
A4: Conservative | B4: Rural Bank contribution before RB-002 | C4: =$C2 -> 3703.94 | D4: =$D2 -> 9827.71 | E4: =$E2 -> 19511.33 | F4: =$F2 -> 30190.85 | G4: =$G2 -> 39874.46
A5: Base | B5: Rural Bank core revenue | C5: =(('04_Adoption'!$C$13*'06_Pricing'!$C$16)*'06_Pricing'!$C$17+('04_Adoption'!$C$12*'04_Adoption'!$C$11*'06_Pricing'!$C$19)*'06_Pricing'!$C$20+'05_Payroll_Activity'!$C$6*'06_Pricing'!$C$23)*(1-'06_Pricing'!$C$27) -> 51955.68 | D5: =(('04_Adoption'!$D$13*'06_Pricing'!$C$16)*'06_Pricing'!$C$17+('04_Adoption'!$D$12*'04_Adoption'!$D$11*'06_Pricing'!$C$19)*'06_Pricing'!$C$20+'05_Payroll_Activity'!$D$6*'06_Pricing'!$C$23)*(1-'06_Pricing'!$C$27) -> 139087.87 | E5: =(('04_Adoption'!$E$13*'06_Pricing'!$C$16)*'06_Pricing'!$C$17+('04_Adoption'!$E$12*'04_Adoption'!$E$11*'06_Pricing'!$C$19)*'06_Pricing'!$C$20+'05_Payroll_Activity'!$E$6*'06_Pricing'!$C$23)*(1-'06_Pricing'!$C$27) -> 249951.74 | F5: =(('04_Adoption'!$F$13*'06_Pricing'!$C$16)*'06_Pricing'!$C$17+('04_Adoption'!$F$12*'04_Adoption'!$F$11*'06_Pricing'!$C$19)*'06_Pricing'!$C$20+'05_Payroll_Activity'!$F$6*'06_Pricing'!$C$23)*(1-'06_Pricing'!$C$27) -> 422390.98 | G5: =(('04_Adoption'!$G$13*'06_Pricing'!$C$16)*'06_Pricing'!$C$17+('04_Adoption'!$G$12*'04_Adoption'!$G$11*'06_Pricing'!$C$19)*'06_Pricing'!$C$20+'05_Payroll_Activity'!$G$6*'06_Pricing'!$C$23)*(1-'06_Pricing'!$C$27) -> 653667.84
A6: Base | B6: Rural Bank SMS margin | C6: ='13_SMS_Variant'!$C$10 -> 919.3 | D6: ='13_SMS_Variant'!$D$10 -> 3432.04 | E6: ='13_SMS_Variant'!$E$10 -> 6864.08 | F6: ='13_SMS_Variant'!$F$10 -> 12134.71 | G6: ='13_SMS_Variant'!$G$10 -> 19611.65
A7: Base | B7: Rural Bank contribution before RB-002 | C7: =$C5 -> 51955.68 | D7: =$D5 -> 139087.87 | E7: =$E5 -> 249951.74 | F7: =$F5 -> 422390.98 | G7: =$G5 -> 653667.84
A8: Accelerated | B8: Rural Bank core revenue | C8: =(('04_Adoption'!$C$19*'06_Pricing'!$C$30)*'06_Pricing'!$C$31+('04_Adoption'!$C$18*'04_Adoption'!$C$17*'06_Pricing'!$C$33)*'06_Pricing'!$C$34+'05_Payroll_Activity'!$C$9*'06_Pricing'!$C$37)*(1-'06_Pricing'!$C$41) -> 323513.31 | D8: =(('04_Adoption'!$D$19*'06_Pricing'!$C$30)*'06_Pricing'!$C$31+('04_Adoption'!$D$18*'04_Adoption'!$D$17*'06_Pricing'!$C$33)*'06_Pricing'!$C$34+'05_Payroll_Activity'!$D$9*'06_Pricing'!$C$37)*(1-'06_Pricing'!$C$41) -> 766448.18 | E8: =(('04_Adoption'!$E$19*'06_Pricing'!$C$30)*'06_Pricing'!$C$31+('04_Adoption'!$E$18*'04_Adoption'!$E$17*'06_Pricing'!$C$33)*'06_Pricing'!$C$34+'05_Payroll_Activity'!$E$9*'06_Pricing'!$C$37)*(1-'06_Pricing'!$C$41) -> 1406479.9 | F8: =(('04_Adoption'!$F$19*'06_Pricing'!$C$30)*'06_Pricing'!$C$31+('04_Adoption'!$F$18*'04_Adoption'!$F$17*'06_Pricing'!$C$33)*'06_Pricing'!$C$34+'05_Payroll_Activity'!$F$9*'06_Pricing'!$C$37)*(1-'06_Pricing'!$C$41) -> 2260973.1 | G8: =(('04_Adoption'!$G$19*'06_Pricing'!$C$30)*'06_Pricing'!$C$31+('04_Adoption'!$G$18*'04_Adoption'!$G$17*'06_Pricing'!$C$33)*'06_Pricing'!$C$34+'05_Payroll_Activity'!$G$9*'06_Pricing'!$C$37)*(1-'06_Pricing'!$C$41) -> 3162075.8
A9: Accelerated | B9: Rural Bank SMS margin | C9: ='13_SMS_Variant'!$C$15 -> 11872.16 | D9: ='13_SMS_Variant'!$D$15 -> 36181.81 | E9: ='13_SMS_Variant'!$E$15 -> 71232.94 | F9: ='13_SMS_Variant'!$F$15 -> 118721.57 | G9: ='13_SMS_Variant'!$G$15 -> 169602.25
A10: Accelerated | B10: Rural Bank contribution before RB-002 | C10: =$C8 -> 323513.31 | D10: =$D8 -> 766448.18 | E10: =$E8 -> 1406479.9 | F10: =$F8 -> 2260973.1 | G10: =$G8 -> 3162075.8

Sheet 11_ODTI_View
A1: Scenario | B1: Metric | C1: Year 1 | D1: Year 2 | E1: Year 3 | F1: Year 4 | G1: Year 5
A2: Conservative | B2: ODTI core revenue | C2: ='04_Adoption'!$C$2*'06_Pricing'!$C$11+('04_Adoption'!$C$4*'04_Adoption'!$C$5*'06_Pricing'!$C$12)/12+(('04_Adoption'!$C$7*'06_Pricing'!$C$2)*'06_Pricing'!$C$4+('04_Adoption'!$C$6*'04_Adoption'!$C$5*'06_Pricing'!$C$5)*'06_Pricing'!$C$7+'05_Payroll_Activity'!$C$3*'06_Pricing'!$C$10)*(1-'06_Pricing'!$C$13) -> 124415.9 | D2: ='04_Adoption'!$D$2*'06_Pricing'!$C$11+('04_Adoption'!$D$4*'04_Adoption'!$D$5*'06_Pricing'!$C$12)/12+(('04_Adoption'!$D$7*'06_Pricing'!$C$2)*'06_Pricing'!$C$4+('04_Adoption'!$D$6*'04_Adoption'!$D$5*'06_Pricing'!$C$5)*'06_Pricing'!$C$7+'05_Payroll_Activity'!$D$3*'06_Pricing'!$C$10)*(1-'06_Pricing'!$C$13) -> 249611.57 | E2: ='04_Adoption'!$E$2*'06_Pricing'!$C$11+('04_Adoption'!$E$4*'04_Adoption'!$E$5*'06_Pricing'!$C$12)/12+(('04_Adoption'!$E$7*'06_Pricing'!$C$2)*'06_Pricing'!$C$4+('04_Adoption'!$E$6*'04_Adoption'!$E$5*'06_Pricing'!$C$5)*'06_Pricing'!$C$7+'05_Payroll_Activity'!$E$3*'06_Pricing'!$C$10)*(1-'06_Pricing'!$C$13) -> 427296.99 | F2: ='04_Adoption'!$F$2*'06_Pricing'!$C$11+('04_Adoption'!$F$4*'04_Adoption'!$F$5*'06_Pricing'!$C$12)/12+(('04_Adoption'!$F$7*'06_Pricing'!$C$2)*'06_Pricing'!$C$4+('04_Adoption'!$F$6*'04_Adoption'!$F$5*'06_Pricing'!$C$5)*'06_Pricing'!$C$7+'05_Payroll_Activity'!$F$3*'06_Pricing'!$C$10)*(1-'06_Pricing'!$C$13) -> 584766.27 | G2: ='04_Adoption'!$G$2*'06_Pricing'!$C$11+('04_Adoption'!$G$4*'04_Adoption'!$G$5*'06_Pricing'!$C$12)/12+(('04_Adoption'!$G$7*'06_Pricing'!$C$2)*'06_Pricing'!$C$4+('04_Adoption'!$G$6*'04_Adoption'!$G$5*'06_Pricing'!$C$5)*'06_Pricing'!$C$7+'05_Payroll_Activity'!$G$3*'06_Pricing'!$C$10)*(1-'06_Pricing'!$C$13) -> 762451.7
A3: Conservative | B3: ODTI contribution - pre-tax/pre-royalty/NetBank-fee-blocked | C3: =$C2-('04_Adoption'!$C$2*'02_Assumptions'!$F$31+'04_Adoption'!$C$4*'04_Adoption'!$C$5*'02_Assumptions'!$F$30) -> 72415.9 | D3: =$D2-('04_Adoption'!$D$2*'02_Assumptions'!$F$31+'04_Adoption'!$D$4*'04_Adoption'!$D$5*'02_Assumptions'!$F$30) -> 135611.57 | E3: =$E2-('04_Adoption'!$E$2*'02_Assumptions'!$F$31+'04_Adoption'!$E$4*'04_Adoption'!$E$5*'02_Assumptions'!$F$30) -> 221296.99 | F3: =$F2-('04_Adoption'!$F$2*'02_Assumptions'!$F$31+'04_Adoption'!$F$4*'04_Adoption'!$F$5*'02_Assumptions'!$F$30) -> 288766.27 | G3: =$G2-('04_Adoption'!$G$2*'02_Assumptions'!$F$31+'04_Adoption'!$G$4*'04_Adoption'!$G$5*'02_Assumptions'!$F$30) -> 374451.7
A4: Conservative | B4: Blocked exclusions | C4: TAX-001; ROY-001; NET-001 blocked | D4: TAX-001; ROY-001; NET-001 blocked | E4: TAX-001; ROY-001; NET-001 blocked | F4: TAX-001; ROY-001; NET-001 blocked | G4: TAX-001; ROY-001; NET-001 blocked
A5: Base | B5: ODTI core revenue | C5: ='04_Adoption'!$C$8*'06_Pricing'!$C$25+('04_Adoption'!$C$10*'04_Adoption'!$C$11*'06_Pricing'!$C$26)/12+(('04_Adoption'!$C$13*'06_Pricing'!$C$16)*'06_Pricing'!$C$18+('04_Adoption'!$C$12*'04_Adoption'!$C$11*'06_Pricing'!$C$19)*'06_Pricing'!$C$21+'05_Payroll_Activity'!$C$6*'06_Pricing'!$C$24)*(1-'06_Pricing'!$C$27) -> 381871.36 | D5: ='04_Adoption'!$D$8*'06_Pricing'!$C$25+('04_Adoption'!$D$10*'04_Adoption'!$D$11*'06_Pricing'!$C$26)/12+(('04_Adoption'!$D$13*'06_Pricing'!$C$16)*'06_Pricing'!$C$18+('04_Adoption'!$D$12*'04_Adoption'!$D$11*'06_Pricing'!$C$19)*'06_Pricing'!$C$21+'05_Payroll_Activity'!$D$6*'06_Pricing'!$C$24)*(1-'06_Pricing'!$C$27) -> 759999.74 | E5: ='04_Adoption'!$E$8*'06_Pricing'!$C$25+('04_Adoption'!$E$10*'04_Adoption'!$E$11*'06_Pricing'!$C$26)/12+(('04_Adoption'!$E$13*'06_Pricing'!$C$16)*'06_Pricing'!$C$18+('04_Adoption'!$E$12*'04_Adoption'!$E$11*'06_Pricing'!$C$19)*'06_Pricing'!$C$21+'05_Payroll_Activity'!$E$6*'06_Pricing'!$C$24)*(1-'06_Pricing'!$C$27) -> 1177663.5 | F5: ='04_Adoption'!$F$8*'06_Pricing'!$C$25+('04_Adoption'!$F$10*'04_Adoption'!$F$11*'06_Pricing'!$C$26)/12+(('04_Adoption'!$F$13*'06_Pricing'!$C$16)*'06_Pricing'!$C$18+('04_Adoption'!$F$12*'04_Adoption'!$F$11*'06_Pricing'!$C$19)*'06_Pricing'!$C$21+'05_Payroll_Activity'!$F$6*'06_Pricing'!$C$24)*(1-'06_Pricing'!$C$27) -> 1845565.9 | G5: ='04_Adoption'!$G$8*'06_Pricing'!$C$25+('04_Adoption'!$G$10*'04_Adoption'!$G$11*'06_Pricing'!$C$26)/12+(('04_Adoption'!$G$13*'06_Pricing'!$C$16)*'06_Pricing'!$C$18+('04_Adoption'!$G$12*'04_Adoption'!$G$11*'06_Pricing'!$C$19)*'06_Pricing'!$C$21+'05_Payroll_Activity'!$G$6*'06_Pricing'!$C$24)*(1-'06_Pricing'!$C$27) -> 2631175.7
A6: Base | B6: ODTI contribution - pre-tax/pre-royalty/NetBank-fee-blocked | C6: =$C5-('04_Adoption'!$C$8*'02_Assumptions'!$G$31+'04_Adoption'!$C$10*'04_Adoption'!$C$11*'02_Assumptions'!$G$30) -> 269371.36 | D6: =$D5-('04_Adoption'!$D$8*'02_Assumptions'!$G$31+'04_Adoption'!$D$10*'04_Adoption'!$D$11*'02_Assumptions'!$G$30) -> 514999.74 | E6: =$E5-('04_Adoption'!$E$8*'02_Assumptions'!$G$31+'04_Adoption'!$E$10*'04_Adoption'!$E$11*'02_Assumptions'!$G$30) -> 777663.49 | F6: =$F5-('04_Adoption'!$F$8*'02_Assumptions'!$G$31+'04_Adoption'!$F$10*'04_Adoption'!$F$11*'02_Assumptions'!$G$30) -> 1200565.9 | G6: =$G5-('04_Adoption'!$G$8*'02_Assumptions'!$G$31+'04_Adoption'!$G$10*'04_Adoption'!$G$11*'02_Assumptions'!$G$30) -> 1681175.7
A7: Base | B7: Blocked exclusions | C7: TAX-001; ROY-001; NET-001 blocked | D7: TAX-001; ROY-001; NET-001 blocked | E7: TAX-001; ROY-001; NET-001 blocked | F7: TAX-001; ROY-001; NET-001 blocked | G7: TAX-001; ROY-001; NET-001 blocked
A8: Accelerated | B8: ODTI core revenue | C8: ='04_Adoption'!$C$14*'06_Pricing'!$C$39+('04_Adoption'!$C$16*'04_Adoption'!$C$17*'06_Pricing'!$C$40)/12+(('04_Adoption'!$C$19*'06_Pricing'!$C$30)*'06_Pricing'!$C$32+('04_Adoption'!$C$18*'04_Adoption'!$C$17*'06_Pricing'!$C$33)*'06_Pricing'!$C$35+'05_Payroll_Activity'!$C$9*'06_Pricing'!$C$38)*(1-'06_Pricing'!$C$41) -> 1054014.4 | D8: ='04_Adoption'!$D$14*'06_Pricing'!$C$39+('04_Adoption'!$D$16*'04_Adoption'!$D$17*'06_Pricing'!$C$40)/12+(('04_Adoption'!$D$19*'06_Pricing'!$C$30)*'06_Pricing'!$C$32+('04_Adoption'!$D$18*'04_Adoption'!$D$17*'06_Pricing'!$C$33)*'06_Pricing'!$C$35+'05_Payroll_Activity'!$D$9*'06_Pricing'!$C$38)*(1-'06_Pricing'!$C$41) -> 1959179.1 | E8: ='04_Adoption'!$E$14*'06_Pricing'!$C$39+('04_Adoption'!$E$16*'04_Adoption'!$E$17*'06_Pricing'!$C$40)/12+(('04_Adoption'!$E$19*'06_Pricing'!$C$30)*'06_Pricing'!$C$32+('04_Adoption'!$E$18*'04_Adoption'!$E$17*'06_Pricing'!$C$33)*'06_Pricing'!$C$35+'05_Payroll_Activity'!$E$9*'06_Pricing'!$C$38)*(1-'06_Pricing'!$C$41) -> 3272186.3 | F8: ='04_Adoption'!$F$14*'06_Pricing'!$C$39+('04_Adoption'!$F$16*'04_Adoption'!$F$17*'06_Pricing'!$C$40)/12+(('04_Adoption'!$F$19*'06_Pricing'!$C$30)*'06_Pricing'!$C$32+('04_Adoption'!$F$18*'04_Adoption'!$F$17*'06_Pricing'!$C$33)*'06_Pricing'!$C$35+'05_Payroll_Activity'!$F$9*'06_Pricing'!$C$38)*(1-'06_Pricing'!$C$41) -> 4978903.9 | G8: ='04_Adoption'!$G$14*'06_Pricing'!$C$39+('04_Adoption'!$G$16*'04_Adoption'!$G$17*'06_Pricing'!$C$40)/12+(('04_Adoption'!$G$19*'06_Pricing'!$C$30)*'06_Pricing'!$C$32+('04_Adoption'!$G$18*'04_Adoption'!$G$17*'06_Pricing'!$C$33)*'06_Pricing'!$C$35+'05_Payroll_Activity'!$G$9*'06_Pricing'!$C$38)*(1-'06_Pricing'!$C$41) -> 6725177
A9: Accelerated | B9: ODTI contribution - pre-tax/pre-royalty/NetBank-fee-blocked | C9: =$C8-('04_Adoption'!$C$14*'02_Assumptions'!$H$31+'04_Adoption'!$C$16*'04_Adoption'!$C$17*'02_Assumptions'!$H$30) -> 850014.39 | D9: =$D8-('04_Adoption'!$D$14*'02_Assumptions'!$H$31+'04_Adoption'!$D$16*'04_Adoption'!$D$17*'02_Assumptions'!$H$30) -> 1559179.1 | E9: =$E8-('04_Adoption'!$E$14*'02_Assumptions'!$H$31+'04_Adoption'!$E$16*'04_Adoption'!$E$17*'02_Assumptions'!$H$30) -> 2588186.3 | F9: =$F8-('04_Adoption'!$F$14*'02_Assumptions'!$H$31+'04_Adoption'!$F$16*'04_Adoption'!$F$17*'02_Assumptions'!$H$30) -> 3922903.9 | G9: =$G8-('04_Adoption'!$G$14*'02_Assumptions'!$H$31+'04_Adoption'!$G$16*'04_Adoption'!$G$17*'02_Assumptions'!$H$30) -> 5285177
A10: Accelerated | B10: Blocked exclusions | C10: TAX-001; ROY-001; NET-001 blocked | D10: TAX-001; ROY-001; NET-001 blocked | E10: TAX-001; ROY-001; NET-001 blocked | F10: TAX-001; ROY-001; NET-001 blocked | G10: TAX-001; ROY-001; NET-001 blocked

Sheet 12_DevOps_View
A1: Scenario | B1: Metric | C1: Year 1 | D1: Year 2 | E1: Year 3 | F1: Year 4 | G1: Year 5
A2: Conservative | B2: DevOps revenue | C2: ='04_Adoption'!$C$2*'02_Assumptions'!$F$32+'04_Adoption'!$C$4*'04_Adoption'!$C$5*'02_Assumptions'!$F$33 -> 140000 | D2: ='04_Adoption'!$D$2*'02_Assumptions'!$F$32+'04_Adoption'!$D$4*'04_Adoption'!$D$5*'02_Assumptions'!$F$33 -> 330000 | E2: ='04_Adoption'!$E$2*'02_Assumptions'!$F$32+'04_Adoption'!$E$4*'04_Adoption'!$E$5*'02_Assumptions'!$F$33 -> 620000 | F2: ='04_Adoption'!$F$2*'02_Assumptions'!$F$32+'04_Adoption'!$F$4*'04_Adoption'!$F$5*'02_Assumptions'!$F$33 -> 920000 | G2: ='04_Adoption'!$G$2*'02_Assumptions'!$F$32+'04_Adoption'!$G$4*'04_Adoption'!$G$5*'02_Assumptions'!$F$33 -> 1210000
A3: Conservative | B3: DevOps contribution | C3: =$C2-'04_Adoption'!$C$4*'04_Adoption'!$C$5*'02_Assumptions'!$F$34 -> 108000 | D3: =$D2-'04_Adoption'!$D$4*'04_Adoption'!$D$5*'02_Assumptions'!$F$34 -> 186000 | E3: =$E2-'04_Adoption'!$E$4*'04_Adoption'!$E$5*'02_Assumptions'!$F$34 -> 284000 | F3: =$F2-'04_Adoption'!$F$4*'04_Adoption'!$F$5*'02_Assumptions'!$F$34 -> 344000 | G3: =$G2-'04_Adoption'!$G$4*'04_Adoption'!$G$5*'02_Assumptions'!$F$34 -> 442000
A4: Base | B4: DevOps revenue | C4: ='04_Adoption'!$C$8*'02_Assumptions'!$G$32+'04_Adoption'!$C$10*'04_Adoption'!$C$11*'02_Assumptions'!$G$33 -> 400000 | D4: ='04_Adoption'!$D$8*'02_Assumptions'!$G$32+'04_Adoption'!$D$10*'04_Adoption'!$D$11*'02_Assumptions'!$G$33 -> 910000 | E4: ='04_Adoption'!$E$8*'02_Assumptions'!$G$32+'04_Adoption'!$E$10*'04_Adoption'!$E$11*'02_Assumptions'!$G$33 -> 1520000 | F4: ='04_Adoption'!$F$8*'02_Assumptions'!$G$32+'04_Adoption'!$F$10*'04_Adoption'!$F$11*'02_Assumptions'!$G$33 -> 2480000 | G4: ='04_Adoption'!$G$8*'02_Assumptions'!$G$32+'04_Adoption'!$G$10*'04_Adoption'!$G$11*'02_Assumptions'!$G$33 -> 3700000
A5: Base | B5: DevOps contribution | C5: =$C4-'04_Adoption'!$C$10*'04_Adoption'!$C$11*'02_Assumptions'!$G$34 -> 310000 | D5: =$D4-'04_Adoption'!$D$10*'04_Adoption'!$D$11*'02_Assumptions'!$G$34 -> 574000 | E5: =$E4-'04_Adoption'!$E$10*'04_Adoption'!$E$11*'02_Assumptions'!$G$34 -> 848000 | F5: =$F4-'04_Adoption'!$F$10*'04_Adoption'!$F$11*'02_Assumptions'!$G$34 -> 1292000 | G5: =$G4-'04_Adoption'!$G$10*'04_Adoption'!$G$11*'02_Assumptions'!$G$34 -> 1780000
A6: Accelerated | B6: DevOps revenue | C6: ='04_Adoption'!$C$14*'02_Assumptions'!$H$32+'04_Adoption'!$C$16*'04_Adoption'!$C$17*'02_Assumptions'!$H$33 -> 920000 | D6: ='04_Adoption'!$D$14*'02_Assumptions'!$H$32+'04_Adoption'!$D$16*'04_Adoption'!$D$17*'02_Assumptions'!$H$33 -> 1880000 | E6: ='04_Adoption'!$E$14*'02_Assumptions'!$H$32+'04_Adoption'!$E$16*'04_Adoption'!$E$17*'02_Assumptions'!$H$33 -> 3270000 | F6: ='04_Adoption'!$F$14*'02_Assumptions'!$H$32+'04_Adoption'!$F$16*'04_Adoption'!$F$17*'02_Assumptions'!$H$33 -> 5100000 | G6: ='04_Adoption'!$G$14*'02_Assumptions'!$H$32+'04_Adoption'!$G$16*'04_Adoption'!$G$17*'02_Assumptions'!$H$33 -> 7000000
A7: Accelerated | B7: DevOps contribution | C7: =$C6-'04_Adoption'!$C$16*'04_Adoption'!$C$17*'02_Assumptions'!$H$34 -> 710000 | D7: =$D6-'04_Adoption'!$D$16*'04_Adoption'!$D$17*'02_Assumptions'!$H$34 -> 1240000 | E7: =$E6-'04_Adoption'!$E$16*'04_Adoption'!$E$17*'02_Assumptions'!$H$34 -> 2010000 | F7: =$F6-'04_Adoption'!$F$16*'04_Adoption'!$F$17*'02_Assumptions'!$H$34 -> 3000000 | G7: =$G6-'04_Adoption'!$G$16*'04_Adoption'!$G$17*'02_Assumptions'!$H$34 -> 4000000

Sheet 13_SMS_Variant
A1: Scenario | B1: Metric | C1: Year 1 | D1: Year 2 | E1: Year 3 | F1: Year 4 | G1: Year 5
A2: Conservative | B2: SMS delivered transactions | C2: ='05_Payroll_Activity'!$C$4 -> 33.12 | D2: ='05_Payroll_Activity'!$D$4 -> 149.04 | E2: ='05_Payroll_Activity'!$E$4 -> 347.76 | F2: ='05_Payroll_Activity'!$F$4 -> 596.16 | G2: ='05_Payroll_Activity'!$G$4 -> 794.88
A3: Conservative | B3: SMS customer-facing revenue | C3: ='05_Payroll_Activity'!$C$4*'06_Pricing'!$C$14 -> 33.12 | D3: ='05_Payroll_Activity'!$D$4*'06_Pricing'!$C$14 -> 149.04 | E3: ='05_Payroll_Activity'!$E$4*'06_Pricing'!$C$14 -> 347.76 | F3: ='05_Payroll_Activity'!$F$4*'06_Pricing'!$C$14 -> 596.16 | G3: ='05_Payroll_Activity'!$G$4*'06_Pricing'!$C$14 -> 794.88
A4: Conservative | B4: Collected SMS revenue after non-collection | C4: =$C3*(1-'06_Pricing'!$C$13) -> 31.46 | D4: =$D3*(1-'06_Pricing'!$C$13) -> 141.59 | E4: =$E3*(1-'06_Pricing'!$C$13) -> 330.37 | F4: =$F3*(1-'06_Pricing'!$C$13) -> 566.35 | G4: =$G3*(1-'06_Pricing'!$C$13) -> 755.14
A5: Conservative | B5: SMS wholesale provider cost | C5: ='05_Payroll_Activity'!$C$4*'06_Pricing'!$C$15 -> 23.18 | D5: ='05_Payroll_Activity'!$D$4*'06_Pricing'!$C$15 -> 104.33 | E5: ='05_Payroll_Activity'!$E$4*'06_Pricing'!$C$15 -> 243.43 | F5: ='05_Payroll_Activity'!$F$4*'06_Pricing'!$C$15 -> 417.31 | G5: ='05_Payroll_Activity'!$G$4*'06_Pricing'!$C$15 -> 556.42
A6: Conservative | B6: Rural Bank SMS margin | C6: =$C4-$C5 -> 8.28 | D6: =$D4-$D5 -> 37.26 | E6: =$E4-$E5 -> 86.94 | F6: =$F4-$F5 -> 149.04 | G6: =$G4-$G5 -> 198.72
A7: Base | B7: SMS delivered transactions | C7: ='05_Payroll_Activity'!$C$7 -> 1915.2 | D7: ='05_Payroll_Activity'!$D$7 -> 7150.08 | E7: ='05_Payroll_Activity'!$E$7 -> 14300.16 | F7: ='05_Payroll_Activity'!$F$7 -> 25280.64 | G7: ='05_Payroll_Activity'!$G$7 -> 40857.6
A8: Base | B8: SMS customer-facing revenue | C8: ='05_Payroll_Activity'!$C$7*'06_Pricing'!$C$28 -> 1915.2 | D8: ='05_Payroll_Activity'!$D$7*'06_Pricing'!$C$28 -> 7150.08 | E8: ='05_Payroll_Activity'!$E$7*'06_Pricing'!$C$28 -> 14300.16 | F8: ='05_Payroll_Activity'!$F$7*'06_Pricing'!$C$28 -> 25280.64 | G8: ='05_Payroll_Activity'!$G$7*'06_Pricing'!$C$28 -> 40857.6
A9: Base | B9: Collected SMS revenue after non-collection | C9: =$C8*(1-'06_Pricing'!$C$27) -> 1876.9 | D9: =$D8*(1-'06_Pricing'!$C$27) -> 7007.08 | E9: =$E8*(1-'06_Pricing'!$C$27) -> 14014.16 | F9: =$F8*(1-'06_Pricing'!$C$27) -> 24775.03 | G9: =$G8*(1-'06_Pricing'!$C$27) -> 40040.45
A10: Base | B10: SMS wholesale provider cost | C10: ='05_Payroll_Activity'!$C$7*'06_Pricing'!$C$29 -> 957.6 | D10: ='05_Payroll_Activity'!$D$7*'06_Pricing'!$C$29 -> 3575.04 | E10: ='05_Payroll_Activity'!$E$7*'06_Pricing'!$C$29 -> 7150.08 | F10: ='05_Payroll_Activity'!$F$7*'06_Pricing'!$C$29 -> 12640.32 | G10: ='05_Payroll_Activity'!$G$7*'06_Pricing'!$C$29 -> 20428.8
A11: Base | B11: Rural Bank SMS margin | C11: =$C9-$C10 -> 919.3 | D11: =$D9-$D10 -> 3432.04 | E11: =$E9-$E10 -> 6864.08 | F11: =$F9-$F10 -> 12134.71 | G11: =$G9-$G10 -> 19611.65
A12: Accelerated | B12: SMS delivered transactions | C12: ='05_Payroll_Activity'!$C$10 -> 20122.3 | D12: ='05_Payroll_Activity'!$D$10 -> 61325.11 | E12: ='05_Payroll_Activity'!$E$10 -> 120733.8 | F12: ='05_Payroll_Activity'!$F$10 -> 201223.01 | G12: ='05_Payroll_Activity'!$G$10 -> 287461.44
A13: Accelerated | B13: SMS customer-facing revenue | C13: ='05_Payroll_Activity'!$C$10*'06_Pricing'!$C$42 -> 20122.3 | D13: ='05_Payroll_Activity'!$D$10*'06_Pricing'!$C$42 -> 61325.11 | E13: ='05_Payroll_Activity'!$E$10*'06_Pricing'!$C$42 -> 120733.8 | F13: ='05_Payroll_Activity'!$F$10*'06_Pricing'!$C$42 -> 201223.01 | G13: ='05_Payroll_Activity'!$G$10*'06_Pricing'!$C$42 -> 287461.44
A14: Accelerated | B14: Collected SMS revenue after non-collection | C14: =$C13*(1-'06_Pricing'!$C$41) -> 19921.08 | D14: =$D13*(1-'06_Pricing'!$C$41) -> 60711.86 | E14: =$E13*(1-'06_Pricing'!$C$41) -> 119526.47 | F14: =$F13*(1-'06_Pricing'!$C$41) -> 199210.78 | G14: =$G13*(1-'06_Pricing'!$C$41) -> 284586.83
A15: Accelerated | B15: SMS wholesale provider cost | C15: ='05_Payroll_Activity'!$C$10*'06_Pricing'!$C$43 -> 8048.92 | D15: ='05_Payroll_Activity'!$D$10*'06_Pricing'!$C$43 -> 24530.04 | E15: ='05_Payroll_Activity'!$E$10*'06_Pricing'!$C$43 -> 48293.52 | F15: ='05_Payroll_Activity'!$F$10*'06_Pricing'!$C$43 -> 80489.2 | G15: ='05_Payroll_Activity'!$G$10*'06_Pricing'!$C$43 -> 114984.58
A16: Accelerated | B16: Rural Bank SMS margin | C16: =$C14-$C15 -> 11872.16 | D16: =$D14-$D15 -> 36181.81 | E16: =$E14-$E15 -> 71232.94 | F16: =$F14-$F15 -> 118721.57 | G16: =$G14-$G15 -> 169602.25

Sheet 14_Consolidated_View
A1: Scenario | B1: Metric | C1: Year 1 | D1: Year 2 | E1: Year 3 | F1: Year 4 | G1: Year 5
A2: Conservative | B2: Core external revenue | C2: ='07_Revenue'!$C$5 -> 8547.2 | D2: ='07_Revenue'!$D$5 -> 20462.4 | E2: ='07_Revenue'!$E$5 -> 38745.6 | F2: ='07_Revenue'!$F$5 -> 57849.6 | G2: ='07_Revenue'!$G$5 -> 76132.8
A3: Conservative | B3: Core consolidated contribution before blocked items | C3: ='07_Revenue'!$C$5*(1-'06_Pricing'!$C$13)-('04_Adoption'!$C$2*'02_Assumptions'!$F$31+'04_Adoption'!$C$4*'04_Adoption'!$C$5*'02_Assumptions'!$F$30) -> -43880.16 | D3: ='07_Revenue'!$D$5*(1-'06_Pricing'!$C$13)-('04_Adoption'!$D$2*'02_Assumptions'!$F$31+'04_Adoption'!$D$4*'04_Adoption'!$D$5*'02_Assumptions'!$F$30) -> -94560.72 | E3: ='07_Revenue'!$E$5*(1-'06_Pricing'!$C$13)-('04_Adoption'!$E$2*'02_Assumptions'!$F$31+'04_Adoption'!$E$4*'04_Adoption'!$E$5*'02_Assumptions'!$F$30) -> -169191.68 | F3: ='07_Revenue'!$F$5*(1-'06_Pricing'!$C$13)-('04_Adoption'!$F$2*'02_Assumptions'!$F$31+'04_Adoption'!$F$4*'04_Adoption'!$F$5*'02_Assumptions'!$F$30) -> -241042.88 | G3: ='07_Revenue'!$G$5*(1-'06_Pricing'!$C$13)-('04_Adoption'!$G$2*'02_Assumptions'!$F$31+'04_Adoption'!$G$4*'04_Adoption'!$G$5*'02_Assumptions'!$F$30) -> -315673.84
A4: Conservative | B4: Optional SMS contribution | C4: ='13_SMS_Variant'!$C$6 -> 8.28 | D4: ='13_SMS_Variant'!$D$6 -> 37.26 | E4: ='13_SMS_Variant'!$E$6 -> 86.94 | F4: ='13_SMS_Variant'!$F$6 -> 149.04 | G4: ='13_SMS_Variant'!$G$6 -> 198.72
A5: Conservative | B5: Combined contribution before blocked items | C5: =$C3+$C4 -> -43871.88 | D5: =$D3+$D4 -> -94523.46 | E5: =$E3+$E4 -> -169104.74 | F5: =$F3+$F4 -> -240893.84 | G5: =$G3+$G4 -> -315475.12
A6: Base | B6: Core external revenue | C6: ='07_Revenue'!$C$12 -> 111048 | D6: ='07_Revenue'!$D$12 -> 274579.2 | E6: ='07_Revenue'!$E$12 -> 477158.4 | F6: ='07_Revenue'!$F$12 -> 793833.6 | G6: ='07_Revenue'!$G$12 -> 1209024
A7: Base | B7: Core consolidated contribution before blocked items | C7: ='07_Revenue'!$C$12*(1-'06_Pricing'!$C$27)-('04_Adoption'!$C$8*'02_Assumptions'!$G$31+'04_Adoption'!$C$10*'04_Adoption'!$C$11*'02_Assumptions'!$G$30) -> -3672.96 | D7: ='07_Revenue'!$D$12*(1-'06_Pricing'!$C$27)-('04_Adoption'!$D$8*'02_Assumptions'!$G$31+'04_Adoption'!$D$10*'04_Adoption'!$D$11*'02_Assumptions'!$G$30) -> 24087.62 | E7: ='07_Revenue'!$E$12*(1-'06_Pricing'!$C$27)-('04_Adoption'!$E$8*'02_Assumptions'!$G$31+'04_Adoption'!$E$10*'04_Adoption'!$E$11*'02_Assumptions'!$G$30) -> 67615.23 | F7: ='07_Revenue'!$F$12*(1-'06_Pricing'!$C$27)-('04_Adoption'!$F$8*'02_Assumptions'!$G$31+'04_Adoption'!$F$10*'04_Adoption'!$F$11*'02_Assumptions'!$G$30) -> 132956.93 | G7: ='07_Revenue'!$G$12*(1-'06_Pricing'!$C$27)-('04_Adoption'!$G$8*'02_Assumptions'!$G$31+'04_Adoption'!$G$10*'04_Adoption'!$G$11*'02_Assumptions'!$G$30) -> 234843.52
A8: Base | B8: Optional SMS contribution | C8: ='13_SMS_Variant'!$C$11 -> 919.3 | D8: ='13_SMS_Variant'!$D$11 -> 3432.04 | E8: ='13_SMS_Variant'!$E$11 -> 6864.08 | F8: ='13_SMS_Variant'!$F$11 -> 12134.71 | G8: ='13_SMS_Variant'!$G$11 -> 19611.65
A9: Base | B9: Combined contribution before blocked items | C9: =$C7+$C8 -> -2753.66 | D9: =$D7+$D8 -> 27519.65 | E9: =$E7+$E8 -> 74479.31 | F9: =$F7+$F8 -> 145091.64 | G9: =$G7+$G8 -> 254455.17
A10: Accelerated | B10: Core external revenue | C10: ='07_Revenue'!$C$19 -> 674270.4 | D10: ='07_Revenue'!$D$19 -> 1500633.6 | E10: ='07_Revenue'!$E$19 -> 2695622.4 | F10: ='07_Revenue'!$F$19 -> 4282704 | G10: ='07_Revenue'!$G$19 -> 5946720
A11: Accelerated | B11: Core consolidated contribution before blocked items | C11: ='07_Revenue'!$C$19*(1-'06_Pricing'!$C$41)-('04_Adoption'!$C$14*'02_Assumptions'!$H$31+'04_Adoption'!$C$16*'04_Adoption'!$C$17*'02_Assumptions'!$H$30) -> 463527.7 | D11: ='07_Revenue'!$D$19*(1-'06_Pricing'!$C$41)-('04_Adoption'!$D$14*'02_Assumptions'!$H$31+'04_Adoption'!$D$16*'04_Adoption'!$D$17*'02_Assumptions'!$H$30) -> 1085627.3 | E11: ='07_Revenue'!$E$19*(1-'06_Pricing'!$C$41)-('04_Adoption'!$E$14*'02_Assumptions'!$H$31+'04_Adoption'!$E$16*'04_Adoption'!$E$17*'02_Assumptions'!$H$30) -> 1984666.2 | F11: ='07_Revenue'!$F$19*(1-'06_Pricing'!$C$41)-('04_Adoption'!$F$14*'02_Assumptions'!$H$31+'04_Adoption'!$F$16*'04_Adoption'!$F$17*'02_Assumptions'!$H$30) -> 3183877 | G11: ='07_Revenue'!$G$19*(1-'06_Pricing'!$C$41)-('04_Adoption'!$G$14*'02_Assumptions'!$H$31+'04_Adoption'!$G$16*'04_Adoption'!$G$17*'02_Assumptions'!$H$30) -> 4447252.8
A12: Accelerated | B12: Optional SMS contribution | C12: ='13_SMS_Variant'!$C$16 -> 11872.16 | D12: ='13_SMS_Variant'!$D$16 -> 36181.81 | E12: ='13_SMS_Variant'!$E$16 -> 71232.94 | F12: ='13_SMS_Variant'!$F$16 -> 118721.57 | G12: ='13_SMS_Variant'!$G$16 -> 169602.25
A13: Accelerated | B13: Combined contribution before blocked items | C13: =$C11+$C12 -> 475399.85 | D13: =$D11+$D12 -> 1121809.1 | E13: =$E11+$E12 -> 2055899.1 | F13: =$F11+$F12 -> 3302598.5 | G13: =$G11+$G12 -> 4616855

Sheet 08_Cost_of_Sales
A1: Scenario | B1: Metric | C1: Year 1 | D1: Year 2 | E1: Year 3 | F1: Year 4 | G1: Year 5
A2: Conservative | B2: Core non-collection effect on employer commercial fees | C2: ='07_Revenue'!$C$5*'02_Assumptions'!$F$36 -> 427.36 | D2: ='07_Revenue'!$D$5*'02_Assumptions'!$F$36 -> 1023.12 | E2: ='07_Revenue'!$E$5*'02_Assumptions'!$F$36 -> 1937.28 | F2: ='07_Revenue'!$F$5*'02_Assumptions'!$F$36 -> 2892.48 | G2: ='07_Revenue'!$G$5*'02_Assumptions'!$F$36 -> 3806.64
A3: Conservative | B3: SMS wholesale provider cost | C3: ='13_SMS_Variant'!$C$5 -> 23.18 | D3: ='13_SMS_Variant'!$D$5 -> 104.33 | E3: ='13_SMS_Variant'!$E$5 -> 243.43 | F3: ='13_SMS_Variant'!$F$5 -> 417.31 | G3: ='13_SMS_Variant'!$G$5 -> 556.42
A4: Conservative | B4: Payroll funding pass-through | C4: Excluded from cost of sales | D4: Excluded from cost of sales | E4: Excluded from cost of sales | F4: Excluded from cost of sales | G4: Excluded from cost of sales
A5: Conservative | B5: Other direct provider costs | C5: Blocked - NET-001 | D5: Blocked - NET-001 | E5: Blocked - NET-001 | F5: Blocked - NET-001 | G5: Blocked - NET-001
A6: Conservative | B6: Tax or government amounts | C6: Blocked - TAX-001 | D6: Blocked - TAX-001 | E6: Blocked - TAX-001 | F6: Blocked - TAX-001 | G6: Blocked - TAX-001
A7: Base | B7: Core non-collection effect on employer commercial fees | C7: ='07_Revenue'!$C$12*'02_Assumptions'!$G$36 -> 2220.96 | D7: ='07_Revenue'!$D$12*'02_Assumptions'!$G$36 -> 5491.58 | E7: ='07_Revenue'!$E$12*'02_Assumptions'!$G$36 -> 9543.17 | F7: ='07_Revenue'!$F$12*'02_Assumptions'!$G$36 -> 15876.67 | G7: ='07_Revenue'!$G$12*'02_Assumptions'!$G$36 -> 24180.48
A8: Base | B8: SMS wholesale provider cost | C8: ='13_SMS_Variant'!$C$10 -> 957.6 | D8: ='13_SMS_Variant'!$D$10 -> 3575.04 | E8: ='13_SMS_Variant'!$E$10 -> 7150.08 | F8: ='13_SMS_Variant'!$F$10 -> 12640.32 | G8: ='13_SMS_Variant'!$G$10 -> 20428.8
A9: Base | B9: Payroll funding pass-through | C9: Excluded from cost of sales | D9: Excluded from cost of sales | E9: Excluded from cost of sales | F9: Excluded from cost of sales | G9: Excluded from cost of sales
A10: Base | B10: Other direct provider costs | C10: Blocked - NET-001 | D10: Blocked - NET-001 | E10: Blocked - NET-001 | F10: Blocked - NET-001 | G10: Blocked - NET-001
A11: Base | B11: Tax or government amounts | C11: Blocked - TAX-001 | D11: Blocked - TAX-001 | E11: Blocked - TAX-001 | F11: Blocked - TAX-001 | G11: Blocked - TAX-001
A12: Accelerated | B12: Core non-collection effect on employer commercial fees | C12: ='07_Revenue'!$C$19*'02_Assumptions'!$H$36 -> 6742.7 | D12: ='07_Revenue'!$D$19*'02_Assumptions'!$H$36 -> 15006.34 | E12: ='07_Revenue'!$E$19*'02_Assumptions'!$H$36 -> 26956.22 | F12: ='07_Revenue'!$F$19*'02_Assumptions'!$H$36 -> 42827.04 | G12: ='07_Revenue'!$G$19*'02_Assumptions'!$H$36 -> 59467.2
A13: Accelerated | B13: SMS wholesale provider cost | C13: ='13_SMS_Variant'!$C$15 -> 8048.92 | D13: ='13_SMS_Variant'!$D$15 -> 24530.04 | E13: ='13_SMS_Variant'!$E$15 -> 48293.52 | F13: ='13_SMS_Variant'!$F$15 -> 80489.2 | G13: ='13_SMS_Variant'!$G$15 -> 114984.58
A14: Accelerated | B14: Payroll funding pass-through | C14: Excluded from cost of sales | D14: Excluded from cost of sales | E14: Excluded from cost of sales | F14: Excluded from cost of sales | G14: Excluded from cost of sales
A15: Accelerated | B15: Other direct provider costs | C15: Blocked - NET-001 | D15: Blocked - NET-001 | E15: Blocked - NET-001 | F15: Blocked - NET-001 | G15: Blocked - NET-001
A16: Accelerated | B16: Tax or government amounts | C16: Blocked - TAX-001 | D16: Blocked - TAX-001 | E16: Blocked - TAX-001 | F16: Blocked - TAX-001 | G16: Blocked - TAX-001

Sheet 09_Operating_Expenses
A1: Scenario | B1: Metric | C1: Year 1 | D1: Year 2 | E1: Year 3 | F1: Year 4 | G1: Year 5
A2: Conservative | B2: ODTI implementation cost | C2: ='04_Adoption'!$C$2*'02_Assumptions'!$F$31 -> 40000 | D2: ='04_Adoption'!$D$2*'02_Assumptions'!$F$31 -> 60000 | E2: ='04_Adoption'!$E$2*'02_Assumptions'!$F$31 -> 80000 | F2: ='04_Adoption'!$F$2*'02_Assumptions'!$F$31 -> 80000 | G2: ='04_Adoption'!$G$2*'02_Assumptions'!$F$31 -> 100000
A3: Conservative | B3: ODTI recurring support cost | C3: ='04_Adoption'!$C$4*'04_Adoption'!$C$5*'02_Assumptions'!$F$30 -> 12000 | D3: ='04_Adoption'!$D$4*'04_Adoption'!$D$5*'02_Assumptions'!$F$30 -> 54000 | E3: ='04_Adoption'!$E$4*'04_Adoption'!$E$5*'02_Assumptions'!$F$30 -> 126000 | F3: ='04_Adoption'!$F$4*'04_Adoption'!$F$5*'02_Assumptions'!$F$30 -> 216000 | G3: ='04_Adoption'!$G$4*'04_Adoption'!$G$5*'02_Assumptions'!$F$30 -> 288000
A4: Conservative | B4: ODTI payroll-specific operating cost | C4: =$C2+$C3 -> 52000 | D4: =$D2+$D3 -> 114000 | E4: =$E2+$E3 -> 206000 | F4: =$F2+$F3 -> 296000 | G4: =$G2+$G3 -> 388000
A5: Conservative | B5: DevOps direct recurring cost | C5: ='04_Adoption'!$C$4*'04_Adoption'!$C$5*'02_Assumptions'!$F$34 -> 32000 | D5: ='04_Adoption'!$D$4*'04_Adoption'!$D$5*'02_Assumptions'!$F$34 -> 144000 | E5: ='04_Adoption'!$E$4*'04_Adoption'!$E$5*'02_Assumptions'!$F$34 -> 336000 | F5: ='04_Adoption'!$F$4*'04_Adoption'!$F$5*'02_Assumptions'!$F$34 -> 576000 | G5: ='04_Adoption'!$G$4*'04_Adoption'!$G$5*'02_Assumptions'!$F$34 -> 768000
A6: Conservative | B6: Platform subscription modernization cost | C6: =('04_Adoption'!$C$4*'04_Adoption'!$C$5*'02_Assumptions'!$F$25)/12 -> 20000 | D6: =('04_Adoption'!$D$4*'04_Adoption'!$D$5*'02_Assumptions'!$F$25)/12 -> 90000 | E6: =('04_Adoption'!$E$4*'04_Adoption'!$E$5*'02_Assumptions'!$F$25)/12 -> 210000 | F6: =('04_Adoption'!$F$4*'04_Adoption'!$F$5*'02_Assumptions'!$F$25)/12 -> 360000 | G6: =('04_Adoption'!$G$4*'04_Adoption'!$G$5*'02_Assumptions'!$F$25)/12 -> 480000
A7: Conservative | B7: DevOps setup modernization cost | C7: ='04_Adoption'!$C$2*'02_Assumptions'!$F$32 -> 100000 | D7: ='04_Adoption'!$D$2*'02_Assumptions'!$F$32 -> 150000 | E7: ='04_Adoption'!$E$2*'02_Assumptions'!$F$32 -> 200000 | F7: ='04_Adoption'!$F$2*'02_Assumptions'!$F$32 -> 200000 | G7: ='04_Adoption'!$G$2*'02_Assumptions'!$F$32 -> 250000
A8: Conservative | B8: DevOps recurring modernization cost | C8: ='04_Adoption'!$C$4*'04_Adoption'!$C$5*'02_Assumptions'!$F$33 -> 40000 | D8: ='04_Adoption'!$D$4*'04_Adoption'!$D$5*'02_Assumptions'!$F$33 -> 180000 | E8: ='04_Adoption'!$E$4*'04_Adoption'!$E$5*'02_Assumptions'!$F$33 -> 420000 | F8: ='04_Adoption'!$F$4*'04_Adoption'!$F$5*'02_Assumptions'!$F$33 -> 720000 | G8: ='04_Adoption'!$G$4*'04_Adoption'!$G$5*'02_Assumptions'!$F$33 -> 960000
A9: Conservative | B9: Public-cloud modernization cost | C9: ='04_Adoption'!$C$4*'04_Adoption'!$C$5*'02_Assumptions'!$F$35 -> 16000 | D9: ='04_Adoption'!$D$4*'04_Adoption'!$D$5*'02_Assumptions'!$F$35 -> 72000 | E9: ='04_Adoption'!$E$4*'04_Adoption'!$E$5*'02_Assumptions'!$F$35 -> 168000 | F9: ='04_Adoption'!$F$4*'04_Adoption'!$F$5*'02_Assumptions'!$F$35 -> 288000 | G9: ='04_Adoption'!$G$4*'04_Adoption'!$G$5*'02_Assumptions'!$F$35 -> 384000
A10: Conservative | B10: Shared modernization cost | C10: =$C6+$C7+$C8+$C9 -> 176000 | D10: =$D6+$D7+$D8+$D9 -> 492000 | E10: =$E6+$E7+$E8+$E9 -> 998000 | F10: =$F6+$F7+$F8+$F9 -> 1568000 | G10: =$G6+$G7+$G8+$G9 -> 2074000
A11: Conservative | B11: Rural Bank payroll-specific internal support cost | C11: Blocked - RB-002 | D11: Blocked - RB-002 | E11: Blocked - RB-002 | F11: Blocked - RB-002 | G11: Blocked - RB-002
A12: Base | B12: ODTI implementation cost | C12: ='04_Adoption'!$C$8*'02_Assumptions'!$G$31 -> 75000 | D12: ='04_Adoption'!$D$8*'02_Assumptions'!$G$31 -> 105000 | E12: ='04_Adoption'!$E$8*'02_Assumptions'!$G$31 -> 120000 | F12: ='04_Adoption'!$F$8*'02_Assumptions'!$G$31 -> 150000 | G12: ='04_Adoption'!$G$8*'02_Assumptions'!$G$31 -> 150000
A13: Base | B13: ODTI recurring support cost | C13: ='04_Adoption'!$C$10*'04_Adoption'!$C$11*'02_Assumptions'!$G$30 -> 37500 | D13: ='04_Adoption'!$D$10*'04_Adoption'!$D$11*'02_Assumptions'!$G$30 -> 140000 | E13: ='04_Adoption'!$E$10*'04_Adoption'!$E$11*'02_Assumptions'!$G$30 -> 280000 | F13: ='04_Adoption'!$F$10*'04_Adoption'!$F$11*'02_Assumptions'!$G$30 -> 495000 | G13: ='04_Adoption'!$G$10*'04_Adoption'!$G$11*'02_Assumptions'!$G$30 -> 800000
A14: Base | B14: ODTI payroll-specific operating cost | C14: =$C12+$C13 -> 112500 | D14: =$D12+$D13 -> 245000 | E14: =$E12+$E13 -> 400000 | F14: =$F12+$F13 -> 645000 | G14: =$G12+$G13 -> 950000
A15: Base | B15: DevOps direct recurring cost | C15: ='04_Adoption'!$C$10*'04_Adoption'!$C$11*'02_Assumptions'!$G$34 -> 90000 | D15: ='04_Adoption'!$D$10*'04_Adoption'!$D$11*'02_Assumptions'!$G$34 -> 336000 | E15: ='04_Adoption'!$E$10*'04_Adoption'!$E$11*'02_Assumptions'!$G$34 -> 672000 | F15: ='04_Adoption'!$F$10*'04_Adoption'!$F$11*'02_Assumptions'!$G$34 -> 1188000 | G15: ='04_Adoption'!$G$10*'04_Adoption'!$G$11*'02_Assumptions'!$G$34 -> 1920000
A16: Base | B16: Platform subscription modernization cost | C16: =('04_Adoption'!$C$10*'04_Adoption'!$C$11*'02_Assumptions'!$G$25)/12 -> 75000 | D16: =('04_Adoption'!$D$10*'04_Adoption'!$D$11*'02_Assumptions'!$G$25)/12 -> 280000 | E16: =('04_Adoption'!$E$10*'04_Adoption'!$E$11*'02_Assumptions'!$G$25)/12 -> 560000 | F16: =('04_Adoption'!$F$10*'04_Adoption'!$F$11*'02_Assumptions'!$G$25)/12 -> 990000 | G16: =('04_Adoption'!$G$10*'04_Adoption'!$G$11*'02_Assumptions'!$G$25)/12 -> 1600000
A17: Base | B17: DevOps setup modernization cost | C17: ='04_Adoption'!$C$8*'02_Assumptions'!$G$32 -> 250000 | D17: ='04_Adoption'!$D$8*'02_Assumptions'!$G$32 -> 350000 | E17: ='04_Adoption'!$E$8*'02_Assumptions'!$G$32 -> 400000 | F17: ='04_Adoption'!$F$8*'02_Assumptions'!$G$32 -> 500000 | G17: ='04_Adoption'!$G$8*'02_Assumptions'!$G$32 -> 500000
A18: Base | B18: DevOps recurring modernization cost | C18: ='04_Adoption'!$C$10*'04_Adoption'!$C$11*'02_Assumptions'!$G$33 -> 150000 | D18: ='04_Adoption'!$D$10*'04_Adoption'!$D$11*'02_Assumptions'!$G$33 -> 560000 | E18: ='04_Adoption'!$E$10*'04_Adoption'!$E$11*'02_Assumptions'!$G$33 -> 1120000 | F18: ='04_Adoption'!$F$10*'04_Adoption'!$F$11*'02_Assumptions'!$G$33 -> 1980000 | G18: ='04_Adoption'!$G$10*'04_Adoption'!$G$11*'02_Assumptions'!$G$33 -> 3200000
A19: Base | B19: Public-cloud modernization cost | C19: ='04_Adoption'!$C$10*'04_Adoption'!$C$11*'02_Assumptions'!$G$35 -> 45000 | D19: ='04_Adoption'!$D$10*'04_Adoption'!$D$11*'02_Assumptions'!$G$35 -> 168000 | E19: ='04_Adoption'!$E$10*'04_Adoption'!$E$11*'02_Assumptions'!$G$35 -> 336000 | F19: ='04_Adoption'!$F$10*'04_Adoption'!$F$11*'02_Assumptions'!$G$35 -> 594000 | G19: ='04_Adoption'!$G$10*'04_Adoption'!$G$11*'02_Assumptions'!$G$35 -> 960000
A20: Base | B20: Shared modernization cost | C20: =$C16+$C17+$C18+$C19 -> 520000 | D20: =$D16+$D17+$D18+$D19 -> 1358000 | E20: =$E16+$E17+$E18+$E19 -> 2416000 | F20: =$F16+$F17+$F18+$F19 -> 4064000 | G20: =$G16+$G17+$G18+$G19 -> 6260000
A21: Base | B21: Rural Bank payroll-specific internal support cost | C21: Blocked - RB-002 | D21: Blocked - RB-002 | E21: Blocked - RB-002 | F21: Blocked - RB-002 | G21: Blocked - RB-002
A22: Accelerated | B22: ODTI implementation cost | C22: ='04_Adoption'!$C$14*'02_Assumptions'!$H$31 -> 120000 | D22: ='04_Adoption'!$D$14*'02_Assumptions'!$H$31 -> 144000 | E22: ='04_Adoption'!$E$14*'02_Assumptions'!$H$31 -> 180000 | F22: ='04_Adoption'!$F$14*'02_Assumptions'!$H$31 -> 216000 | G22: ='04_Adoption'!$G$14*'02_Assumptions'!$H$31 -> 240000
A23: Accelerated | B23: ODTI recurring support cost | C23: ='04_Adoption'!$C$16*'04_Adoption'!$C$17*'02_Assumptions'!$H$30 -> 84000 | D23: ='04_Adoption'!$D$16*'04_Adoption'!$D$17*'02_Assumptions'!$H$30 -> 256000 | E23: ='04_Adoption'!$E$16*'04_Adoption'!$E$17*'02_Assumptions'!$H$30 -> 504000 | F23: ='04_Adoption'!$F$16*'04_Adoption'!$F$17*'02_Assumptions'!$H$30 -> 840000 | G23: ='04_Adoption'!$G$16*'04_Adoption'!$G$17*'02_Assumptions'!$H$30 -> 1200000
A24: Accelerated | B24: ODTI payroll-specific operating cost | C24: =$C22+$C23 -> 204000 | D24: =$D22+$D23 -> 400000 | E24: =$E22+$E23 -> 684000 | F24: =$F22+$F23 -> 1056000 | G24: =$G22+$G23 -> 1440000
A25: Accelerated | B25: DevOps direct recurring cost | C25: ='04_Adoption'!$C$16*'04_Adoption'!$C$17*'02_Assumptions'!$H$34 -> 210000 | D25: ='04_Adoption'!$D$16*'04_Adoption'!$D$17*'02_Assumptions'!$H$34 -> 640000 | E25: ='04_Adoption'!$E$16*'04_Adoption'!$E$17*'02_Assumptions'!$H$34 -> 1260000 | F25: ='04_Adoption'!$F$16*'04_Adoption'!$F$17*'02_Assumptions'!$H$34 -> 2100000 | G25: ='04_Adoption'!$G$16*'04_Adoption'!$G$17*'02_Assumptions'!$H$34 -> 3000000
A26: Accelerated | B26: Platform subscription modernization cost | C26: =('04_Adoption'!$C$16*'04_Adoption'!$C$17*'02_Assumptions'!$H$25)/12 -> 210000 | D26: =('04_Adoption'!$D$16*'04_Adoption'!$D$17*'02_Assumptions'!$H$25)/12 -> 640000 | E26: =('04_Adoption'!$E$16*'04_Adoption'!$E$17*'02_Assumptions'!$H$25)/12 -> 1260000 | F26: =('04_Adoption'!$F$16*'04_Adoption'!$F$17*'02_Assumptions'!$H$25)/12 -> 2100000 | G26: =('04_Adoption'!$G$16*'04_Adoption'!$G$17*'02_Assumptions'!$H$25)/12 -> 3000000
A27: Accelerated | B27: DevOps setup modernization cost | C27: ='04_Adoption'!$C$14*'02_Assumptions'!$H$32 -> 500000 | D27: ='04_Adoption'!$D$14*'02_Assumptions'!$H$32 -> 600000 | E27: ='04_Adoption'!$E$14*'02_Assumptions'!$H$32 -> 750000 | F27: ='04_Adoption'!$F$14*'02_Assumptions'!$H$32 -> 900000 | G27: ='04_Adoption'!$G$14*'02_Assumptions'!$H$32 -> 1000000
A28: Accelerated | B28: DevOps recurring modernization cost | C28: ='04_Adoption'!$C$16*'04_Adoption'!$C$17*'02_Assumptions'!$H$33 -> 420000 | D28: ='04_Adoption'!$D$16*'04_Adoption'!$D$17*'02_Assumptions'!$H$33 -> 1280000 | E28: ='04_Adoption'!$E$16*'04_Adoption'!$E$17*'02_Assumptions'!$H$33 -> 2520000 | F28: ='04_Adoption'!$F$16*'04_Adoption'!$F$17*'02_Assumptions'!$H$33 -> 4200000 | G28: ='04_Adoption'!$G$16*'04_Adoption'!$G$17*'02_Assumptions'!$H$33 -> 6000000
A29: Accelerated | B29: Public-cloud modernization cost | C29: ='04_Adoption'!$C$16*'04_Adoption'!$C$17*'02_Assumptions'!$H$35 -> 105000 | D29: ='04_Adoption'!$D$16*'04_Adoption'!$D$17*'02_Assumptions'!$H$35 -> 320000 | E29: ='04_Adoption'!$E$16*'04_Adoption'!$E$17*'02_Assumptions'!$H$35 -> 630000 | F29: ='04_Adoption'!$F$16*'04_Adoption'!$F$17*'02_Assumptions'!$H$35 -> 1050000 | G29: ='04_Adoption'!$G$16*'04_Adoption'!$G$17*'02_Assumptions'!$H$35 -> 1500000
A30: Accelerated | B30: Shared modernization cost | C30: =$C26+$C27+$C28+$C29 -> 1235000 | D30: =$D26+$D27+$D28+$D29 -> 2840000 | E30: =$E26+$E27+$E28+$E29 -> 5160000 | F30: =$F26+$F27+$F28+$F29 -> 8250000 | G30: =$G26+$G27+$G28+$G29 -> 11500000
A31: Accelerated | B31: Rural Bank payroll-specific internal support cost | C31: Blocked - RB-002 | D31: Blocked - RB-002 | E31: Blocked - RB-002 | F31: Blocked - RB-002 | G31: Blocked - RB-002

Sheet 15_Profit_and_Loss
A1: Scenario | B1: Metric | C1: Year 1 | D1: Year 2 | E1: Year 3 | F1: Year 4 | G1: Year 5
A2: Conservative | B2: Rural Bank revenue | C2: ='10_Rural_Bank_View'!$C$2 -> 3703.94 | D2: ='10_Rural_Bank_View'!$D$2 -> 9827.71 | E2: ='10_Rural_Bank_View'!$E$2 -> 19511.33 | F2: ='10_Rural_Bank_View'!$F$2 -> 30190.85 | G2: ='10_Rural_Bank_View'!$G$2 -> 39874.46
A3: Conservative | B3: Rural Bank Contribution Before Internal Bank Payroll-Support Cost | C3: ='10_Rural_Bank_View'!$C$4 -> 3703.94 | D3: ='10_Rural_Bank_View'!$D$4 -> 9827.71 | E3: ='10_Rural_Bank_View'!$E$4 -> 19511.33 | F3: ='10_Rural_Bank_View'!$F$4 -> 30190.85 | G3: ='10_Rural_Bank_View'!$G$4 -> 39874.46
A4: Conservative | B4: Rural Bank true net contribution | C4: Blocked - RB-002 | D4: Blocked - RB-002 | E4: Blocked - RB-002 | F4: Blocked - RB-002 | G4: Blocked - RB-002
A5: Conservative | B5: ODTI revenue | C5: ='11_ODTI_View'!$C$2 -> 124415.9 | D5: ='11_ODTI_View'!$D$2 -> 249611.57 | E5: ='11_ODTI_View'!$E$2 -> 427296.99 | F5: ='11_ODTI_View'!$F$2 -> 584766.27 | G5: ='11_ODTI_View'!$G$2 -> 762451.7
A6: Conservative | B6: ODTI operating expenses | C6: ='09_Operating_Expenses'!$C$4 -> 52000 | D6: ='09_Operating_Expenses'!$D$4 -> 114000 | E6: ='09_Operating_Expenses'!$E$4 -> 206000 | F6: ='09_Operating_Expenses'!$F$4 -> 296000 | G6: ='09_Operating_Expenses'!$G$4 -> 388000
A7: Conservative | B7: ODTI contribution - Pre-Tax, Pre-Royalty, NetBank-Fee-Blocked | C7: ='11_ODTI_View'!$C$3 -> 72415.9 | D7: ='11_ODTI_View'!$D$3 -> 135611.57 | E7: ='11_ODTI_View'!$E$3 -> 221296.99 | F7: ='11_ODTI_View'!$F$3 -> 288766.27 | G7: ='11_ODTI_View'!$G$3 -> 374451.7
A8: Conservative | B8: DevOps revenue | C8: ='12_DevOps_View'!$C$2 -> 140000 | D8: ='12_DevOps_View'!$D$2 -> 330000 | E8: ='12_DevOps_View'!$E$2 -> 620000 | F8: ='12_DevOps_View'!$F$2 -> 920000 | G8: ='12_DevOps_View'!$G$2 -> 1210000
A9: Conservative | B9: DevOps direct cost | C9: ='09_Operating_Expenses'!$C$5 -> 32000 | D9: ='09_Operating_Expenses'!$D$5 -> 144000 | E9: ='09_Operating_Expenses'!$E$5 -> 336000 | F9: ='09_Operating_Expenses'!$F$5 -> 576000 | G9: ='09_Operating_Expenses'!$G$5 -> 768000
A10: Conservative | B10: DevOps contribution | C10: ='12_DevOps_View'!$C$3 -> 108000 | D10: ='12_DevOps_View'!$D$3 -> 186000 | E10: ='12_DevOps_View'!$E$3 -> 284000 | F10: ='12_DevOps_View'!$F$3 -> 344000 | G10: ='12_DevOps_View'!$G$3 -> 442000
A11: Conservative | B11: Consolidated external revenue | C11: ='14_Consolidated_View'!$C$2 -> 8547.2 | D11: ='14_Consolidated_View'!$D$2 -> 20462.4 | E11: ='14_Consolidated_View'!$E$2 -> 38745.6 | F11: ='14_Consolidated_View'!$F$2 -> 57849.6 | G11: ='14_Consolidated_View'!$G$2 -> 76132.8
A12: Conservative | B12: Consolidated contribution before blocked items | C12: ='14_Consolidated_View'!$C$3 -> -43880.16 | D12: ='14_Consolidated_View'!$D$3 -> -94560.72 | E12: ='14_Consolidated_View'!$E$3 -> -169191.68 | F12: ='14_Consolidated_View'!$F$3 -> -241042.88 | G12: ='14_Consolidated_View'!$G$3 -> -315673.84
A13: Conservative | B13: Tax-adjusted net income | C13: Blocked - TAX-001 | D13: Blocked - TAX-001 | E13: Blocked - TAX-001 | F13: Blocked - TAX-001 | G13: Blocked - TAX-001
A14: Conservative | B14: Formal GAAP/PFRS net income | C14: Blocked - accounting treatment unresolved | D14: Blocked - accounting treatment unresolved | E14: Blocked - accounting treatment unresolved | F14: Blocked - accounting treatment unresolved | G14: Blocked - accounting treatment unresolved
A15: Base | B15: Rural Bank revenue | C15: ='10_Rural_Bank_View'!$C$5 -> 51955.68 | D15: ='10_Rural_Bank_View'!$D$5 -> 139087.87 | E15: ='10_Rural_Bank_View'!$E$5 -> 249951.74 | F15: ='10_Rural_Bank_View'!$F$5 -> 422390.98 | G15: ='10_Rural_Bank_View'!$G$5 -> 653667.84
A16: Base | B16: Rural Bank Contribution Before Internal Bank Payroll-Support Cost | C16: ='10_Rural_Bank_View'!$C$7 -> 51955.68 | D16: ='10_Rural_Bank_View'!$D$7 -> 139087.87 | E16: ='10_Rural_Bank_View'!$E$7 -> 249951.74 | F16: ='10_Rural_Bank_View'!$F$7 -> 422390.98 | G16: ='10_Rural_Bank_View'!$G$7 -> 653667.84
A17: Base | B17: Rural Bank true net contribution | C17: Blocked - RB-002 | D17: Blocked - RB-002 | E17: Blocked - RB-002 | F17: Blocked - RB-002 | G17: Blocked - RB-002
A18: Base | B18: ODTI revenue | C18: ='11_ODTI_View'!$C$5 -> 381871.36 | D18: ='11_ODTI_View'!$D$5 -> 759999.74 | E18: ='11_ODTI_View'!$E$5 -> 1177663.5 | F18: ='11_ODTI_View'!$F$5 -> 1845565.9 | G18: ='11_ODTI_View'!$G$5 -> 2631175.7
A19: Base | B19: ODTI operating expenses | C19: ='09_Operating_Expenses'!$C$14 -> 112500 | D19: ='09_Operating_Expenses'!$D$14 -> 245000 | E19: ='09_Operating_Expenses'!$E$14 -> 400000 | F19: ='09_Operating_Expenses'!$F$14 -> 645000 | G19: ='09_Operating_Expenses'!$G$14 -> 950000
A20: Base | B20: ODTI contribution - Pre-Tax, Pre-Royalty, NetBank-Fee-Blocked | C20: ='11_ODTI_View'!$C$6 -> 269371.36 | D20: ='11_ODTI_View'!$D$6 -> 514999.74 | E20: ='11_ODTI_View'!$E$6 -> 777663.49 | F20: ='11_ODTI_View'!$F$6 -> 1200565.9 | G20: ='11_ODTI_View'!$G$6 -> 1681175.7
A21: Base | B21: DevOps revenue | C21: ='12_DevOps_View'!$C$4 -> 400000 | D21: ='12_DevOps_View'!$D$4 -> 910000 | E21: ='12_DevOps_View'!$E$4 -> 1520000 | F21: ='12_DevOps_View'!$F$4 -> 2480000 | G21: ='12_DevOps_View'!$G$4 -> 3700000
A22: Base | B22: DevOps direct cost | C22: ='09_Operating_Expenses'!$C$15 -> 90000 | D22: ='09_Operating_Expenses'!$D$15 -> 336000 | E22: ='09_Operating_Expenses'!$E$15 -> 672000 | F22: ='09_Operating_Expenses'!$F$15 -> 1188000 | G22: ='09_Operating_Expenses'!$G$15 -> 1920000
A23: Base | B23: DevOps contribution | C23: ='12_DevOps_View'!$C$5 -> 310000 | D23: ='12_DevOps_View'!$D$5 -> 574000 | E23: ='12_DevOps_View'!$E$5 -> 848000 | F23: ='12_DevOps_View'!$F$5 -> 1292000 | G23: ='12_DevOps_View'!$G$5 -> 1780000
A24: Base | B24: Consolidated external revenue | C24: ='14_Consolidated_View'!$C$6 -> 111048 | D24: ='14_Consolidated_View'!$D$6 -> 274579.2 | E24: ='14_Consolidated_View'!$E$6 -> 477158.4 | F24: ='14_Consolidated_View'!$F$6 -> 793833.6 | G24: ='14_Consolidated_View'!$G$6 -> 1209024
A25: Base | B25: Consolidated contribution before blocked items | C25: ='14_Consolidated_View'!$C$7 -> -3672.96 | D25: ='14_Consolidated_View'!$D$7 -> 24087.62 | E25: ='14_Consolidated_View'!$E$7 -> 67615.23 | F25: ='14_Consolidated_View'!$F$7 -> 132956.93 | G25: ='14_Consolidated_View'!$G$7 -> 234843.52
A26: Base | B26: Tax-adjusted net income | C26: Blocked - TAX-001 | D26: Blocked - TAX-001 | E26: Blocked - TAX-001 | F26: Blocked - TAX-001 | G26: Blocked - TAX-001
A27: Base | B27: Formal GAAP/PFRS net income | C27: Blocked - accounting treatment unresolved | D27: Blocked - accounting treatment unresolved | E27: Blocked - accounting treatment unresolved | F27: Blocked - accounting treatment unresolved | G27: Blocked - accounting treatment unresolved
A28: Accelerated | B28: Rural Bank revenue | C28: ='10_Rural_Bank_View'!$C$8 -> 323513.31 | D28: ='10_Rural_Bank_View'!$D$8 -> 766448.18 | E28: ='10_Rural_Bank_View'!$E$8 -> 1406479.9 | F28: ='10_Rural_Bank_View'!$F$8 -> 2260973.1 | G28: ='10_Rural_Bank_View'!$G$8 -> 3162075.8
A29: Accelerated | B29: Rural Bank Contribution Before Internal Bank Payroll-Support Cost | C29: ='10_Rural_Bank_View'!$C$10 -> 323513.31 | D29: ='10_Rural_Bank_View'!$D$10 -> 766448.18 | E29: ='10_Rural_Bank_View'!$E$10 -> 1406479.9 | F29: ='10_Rural_Bank_View'!$F$10 -> 2260973.1 | G29: ='10_Rural_Bank_View'!$G$10 -> 3162075.8
A30: Accelerated | B30: Rural Bank true net contribution | C30: Blocked - RB-002 | D30: Blocked - RB-002 | E30: Blocked - RB-002 | F30: Blocked - RB-002 | G30: Blocked - RB-002
A31: Accelerated | B31: ODTI revenue | C31: ='11_ODTI_View'!$C$8 -> 1054014.4 | D31: ='11_ODTI_View'!$D$8 -> 1959179.1 | E31: ='11_ODTI_View'!$E$8 -> 3272186.3 | F31: ='11_ODTI_View'!$F$8 -> 4978903.9 | G31: ='11_ODTI_View'!$G$8 -> 6725177
A32: Accelerated | B32: ODTI operating expenses | C32: ='09_Operating_Expenses'!$C$24 -> 204000 | D32: ='09_Operating_Expenses'!$D$24 -> 400000 | E32: ='09_Operating_Expenses'!$E$24 -> 684000 | F32: ='09_Operating_Expenses'!$F$24 -> 1056000 | G32: ='09_Operating_Expenses'!$G$24 -> 1440000
A33: Accelerated | B33: ODTI contribution - Pre-Tax, Pre-Royalty, NetBank-Fee-Blocked | C33: ='11_ODTI_View'!$C$9 -> 850014.39 | D33: ='11_ODTI_View'!$D$9 -> 1559179.1 | E33: ='11_ODTI_View'!$E$9 -> 2588186.3 | F33: ='11_ODTI_View'!$F$9 -> 3922903.9 | G33: ='11_ODTI_View'!$G$9 -> 5285177
A34: Accelerated | B34: DevOps revenue | C34: ='12_DevOps_View'!$C$6 -> 920000 | D34: ='12_DevOps_View'!$D$6 -> 1880000 | E34: ='12_DevOps_View'!$E$6 -> 3270000 | F34: ='12_DevOps_View'!$F$6 -> 5100000 | G34: ='12_DevOps_View'!$G$6 -> 7000000
A35: Accelerated | B35: DevOps direct cost | C35: ='09_Operating_Expenses'!$C$25 -> 210000 | D35: ='09_Operating_Expenses'!$D$25 -> 640000 | E35: ='09_Operating_Expenses'!$E$25 -> 1260000 | F35: ='09_Operating_Expenses'!$F$25 -> 2100000 | G35: ='09_Operating_Expenses'!$G$25 -> 3000000
A36: Accelerated | B36: DevOps contribution | C36: ='12_DevOps_View'!$C$7 -> 710000 | D36: ='12_DevOps_View'!$D$7 -> 1240000 | E36: ='12_DevOps_View'!$E$7 -> 2010000 | F36: ='12_DevOps_View'!$F$7 -> 3000000 | G36: ='12_DevOps_View'!$G$7 -> 4000000
A37: Accelerated | B37: Consolidated external revenue | C37: ='14_Consolidated_View'!$C$10 -> 674270.4 | D37: ='14_Consolidated_View'!$D$10 -> 1500633.6 | E37: ='14_Consolidated_View'!$E$10 -> 2695622.4 | F37: ='14_Consolidated_View'!$F$10 -> 4282704 | G37: ='14_Consolidated_View'!$G$10 -> 5946720
A38: Accelerated | B38: Consolidated contribution before blocked items | C38: ='14_Consolidated_View'!$C$11 -> 463527.7 | D38: ='14_Consolidated_View'!$D$11 -> 1085627.3 | E38: ='14_Consolidated_View'!$E$11 -> 1984666.2 | F38: ='14_Consolidated_View'!$F$11 -> 3183877 | G38: ='14_Consolidated_View'!$G$11 -> 4447252.8
A39: Accelerated | B39: Tax-adjusted net income | C39: Blocked - TAX-001 | D39: Blocked - TAX-001 | E39: Blocked - TAX-001 | F39: Blocked - TAX-001 | G39: Blocked - TAX-001
A40: Accelerated | B40: Formal GAAP/PFRS net income | C40: Blocked - accounting treatment unresolved | D40: Blocked - accounting treatment unresolved | E40: Blocked - accounting treatment unresolved | F40: Blocked - accounting treatment unresolved | G40: Blocked - accounting treatment unresolved

Sheet 16_Cash_Flow
A1: Scenario | B1: Metric | C1: Year 1 | D1: Year 2 | E1: Year 3 | F1: Year 4 | G1: Year 5
A2: Conservative | B2: Recognized core external revenue | C2: ='07_Revenue'!$C$5 -> 8547.2 | D2: ='07_Revenue'!$D$5 -> 20462.4 | E2: ='07_Revenue'!$E$5 -> 38745.6 | F2: ='07_Revenue'!$F$5 -> 57849.6 | G2: ='07_Revenue'!$G$5 -> 76132.8
A3: Conservative | B3: Collected core commercial fees after non-collection | C3: ='07_Revenue'!$C$5*(1-'02_Assumptions'!$F$36) -> 8119.84 | D3: ='07_Revenue'!$D$5*(1-'02_Assumptions'!$F$36) -> 19439.28 | E3: ='07_Revenue'!$E$5*(1-'02_Assumptions'!$F$36) -> 36808.32 | F3: ='07_Revenue'!$F$5*(1-'02_Assumptions'!$F$36) -> 54957.12 | G3: ='07_Revenue'!$G$5*(1-'02_Assumptions'!$F$36) -> 72326.16
A4: Conservative | B4: ODTI payroll-specific cash cost before timing | C4: ='09_Operating_Expenses'!$C$4 -> 52000 | D4: ='09_Operating_Expenses'!$D$4 -> 114000 | E4: ='09_Operating_Expenses'!$E$4 -> 206000 | F4: ='09_Operating_Expenses'!$F$4 -> 296000 | G4: ='09_Operating_Expenses'!$G$4 -> 388000
A5: Conservative | B5: External cloud cash payment before timing | C5: ='09_Operating_Expenses'!$C$9 -> 16000 | D5: ='09_Operating_Expenses'!$D$9 -> 72000 | E5: ='09_Operating_Expenses'!$E$9 -> 168000 | F5: ='09_Operating_Expenses'!$F$9 -> 288000 | G5: ='09_Operating_Expenses'!$G$9 -> 384000
A6: Conservative | B6: Employer collection timing | C6: Blocked - COL-001 | D6: Blocked - COL-001 | E6: Blocked - COL-001 | F6: Blocked - COL-001 | G6: Blocked - COL-001
A7: Conservative | B7: Working-capital roll-forward | C7: Blocked - COL-001 and balance-sheet prerequisites | D7: Blocked - COL-001 and balance-sheet prerequisites | E7: Blocked - COL-001 and balance-sheet prerequisites | F7: Blocked - COL-001 and balance-sheet prerequisites | G7: Blocked - COL-001 and balance-sheet prerequisites
A8: Conservative | B8: Ending cash | C8: Blocked - beginning cash and financing assumptions unavailable | D8: Blocked - beginning cash and financing assumptions unavailable | E8: Blocked - beginning cash and financing assumptions unavailable | F8: Blocked - beginning cash and financing assumptions unavailable | G8: Blocked - beginning cash and financing assumptions unavailable
A9: Base | B9: Recognized core external revenue | C9: ='07_Revenue'!$C$12 -> 111048 | D9: ='07_Revenue'!$D$12 -> 274579.2 | E9: ='07_Revenue'!$E$12 -> 477158.4 | F9: ='07_Revenue'!$F$12 -> 793833.6 | G9: ='07_Revenue'!$G$12 -> 1209024
A10: Base | B10: Collected core commercial fees after non-collection | C10: ='07_Revenue'!$C$12*(1-'02_Assumptions'!$G$36) -> 108827.04 | D10: ='07_Revenue'!$D$12*(1-'02_Assumptions'!$G$36) -> 269087.62 | E10: ='07_Revenue'!$E$12*(1-'02_Assumptions'!$G$36) -> 467615.23 | F10: ='07_Revenue'!$F$12*(1-'02_Assumptions'!$G$36) -> 777956.93 | G10: ='07_Revenue'!$G$12*(1-'02_Assumptions'!$G$36) -> 1184843.5
A11: Base | B11: ODTI payroll-specific cash cost before timing | C11: ='09_Operating_Expenses'!$C$14 -> 112500 | D11: ='09_Operating_Expenses'!$D$14 -> 245000 | E11: ='09_Operating_Expenses'!$E$14 -> 400000 | F11: ='09_Operating_Expenses'!$F$14 -> 645000 | G11: ='09_Operating_Expenses'!$G$14 -> 950000
A12: Base | B12: External cloud cash payment before timing | C12: ='09_Operating_Expenses'!$C$19 -> 45000 | D12: ='09_Operating_Expenses'!$D$19 -> 168000 | E12: ='09_Operating_Expenses'!$E$19 -> 336000 | F12: ='09_Operating_Expenses'!$F$19 -> 594000 | G12: ='09_Operating_Expenses'!$G$19 -> 960000
A13: Base | B13: Employer collection timing | C13: Blocked - COL-001 | D13: Blocked - COL-001 | E13: Blocked - COL-001 | F13: Blocked - COL-001 | G13: Blocked - COL-001
A14: Base | B14: Working-capital roll-forward | C14: Blocked - COL-001 and balance-sheet prerequisites | D14: Blocked - COL-001 and balance-sheet prerequisites | E14: Blocked - COL-001 and balance-sheet prerequisites | F14: Blocked - COL-001 and balance-sheet prerequisites | G14: Blocked - COL-001 and balance-sheet prerequisites
A15: Base | B15: Ending cash | C15: Blocked - beginning cash and financing assumptions unavailable | D15: Blocked - beginning cash and financing assumptions unavailable | E15: Blocked - beginning cash and financing assumptions unavailable | F15: Blocked - beginning cash and financing assumptions unavailable | G15: Blocked - beginning cash and financing assumptions unavailable
A16: Accelerated | B16: Recognized core external revenue | C16: ='07_Revenue'!$C$19 -> 674270.4 | D16: ='07_Revenue'!$D$19 -> 1500633.6 | E16: ='07_Revenue'!$E$19 -> 2695622.4 | F16: ='07_Revenue'!$F$19 -> 4282704 | G16: ='07_Revenue'!$G$19 -> 5946720
A17: Accelerated | B17: Collected core commercial fees after non-collection | C17: ='07_Revenue'!$C$19*(1-'02_Assumptions'!$H$36) -> 667527.7 | D17: ='07_Revenue'!$D$19*(1-'02_Assumptions'!$H$36) -> 1485627.3 | E17: ='07_Revenue'!$E$19*(1-'02_Assumptions'!$H$36) -> 2668666.2 | F17: ='07_Revenue'!$F$19*(1-'02_Assumptions'!$H$36) -> 4239877 | G17: ='07_Revenue'!$G$19*(1-'02_Assumptions'!$H$36) -> 5887252.8
A18: Accelerated | B18: ODTI payroll-specific cash cost before timing | C18: ='09_Operating_Expenses'!$C$24 -> 204000 | D18: ='09_Operating_Expenses'!$D$24 -> 400000 | E18: ='09_Operating_Expenses'!$E$24 -> 684000 | F18: ='09_Operating_Expenses'!$F$24 -> 1056000 | G18: ='09_Operating_Expenses'!$G$24 -> 1440000
A19: Accelerated | B19: External cloud cash payment before timing | C19: ='09_Operating_Expenses'!$C$29 -> 105000 | D19: ='09_Operating_Expenses'!$D$29 -> 320000 | E19: ='09_Operating_Expenses'!$E$29 -> 630000 | F19: ='09_Operating_Expenses'!$F$29 -> 1050000 | G19: ='09_Operating_Expenses'!$G$29 -> 1500000
A20: Accelerated | B20: Employer collection timing | C20: Blocked - COL-001 | D20: Blocked - COL-001 | E20: Blocked - COL-001 | F20: Blocked - COL-001 | G20: Blocked - COL-001
A21: Accelerated | B21: Working-capital roll-forward | C21: Blocked - COL-001 and balance-sheet prerequisites | D21: Blocked - COL-001 and balance-sheet prerequisites | E21: Blocked - COL-001 and balance-sheet prerequisites | F21: Blocked - COL-001 and balance-sheet prerequisites | G21: Blocked - COL-001 and balance-sheet prerequisites
A22: Accelerated | B22: Ending cash | C22: Blocked - beginning cash and financing assumptions unavailable | D22: Blocked - beginning cash and financing assumptions unavailable | E22: Blocked - beginning cash and financing assumptions unavailable | F22: Blocked - beginning cash and financing assumptions unavailable | G22: Blocked - beginning cash and financing assumptions unavailable

Sheet 17_Capital_Budgeting
A1: Scenario | B1: Metric | C1: Year 1 | D1: Year 2 | E1: Year 3 | F1: Year 4 | G1: Year 5
A2: Conservative | B2: Rural Bank modernization investment cash outflow before timing | C2: ='09_Operating_Expenses'!$C$10 -> 176000 | D2: ='09_Operating_Expenses'!$D$10 -> 492000 | E2: ='09_Operating_Expenses'!$E$10 -> 998000 | F2: ='09_Operating_Expenses'!$F$10 -> 1568000 | G2: ='09_Operating_Expenses'!$G$10 -> 2074000
A3: Conservative | B3: Rural Bank incremental cash contribution before RB-002 | C3: ='10_Rural_Bank_View'!$C$4 -> 3703.94 | D3: ='10_Rural_Bank_View'!$D$4 -> 9827.71 | E3: ='10_Rural_Bank_View'!$E$4 -> 19511.33 | F3: ='10_Rural_Bank_View'!$F$4 -> 30190.85 | G3: ='10_Rural_Bank_View'!$G$4 -> 39874.46
A4: Conservative | B4: ODTI program contribution before blocked items | C4: ='11_ODTI_View'!$C$3 -> 72415.9 | D4: ='11_ODTI_View'!$D$3 -> 135611.57 | E4: ='11_ODTI_View'!$E$3 -> 221296.99 | F4: ='11_ODTI_View'!$F$3 -> 288766.27 | G4: ='11_ODTI_View'!$G$3 -> 374451.7
A5: Conservative | B5: DevOps contribution before blocked items | C5: ='12_DevOps_View'!$C$3 -> 108000 | D5: ='12_DevOps_View'!$D$3 -> 186000 | E5: ='12_DevOps_View'!$E$3 -> 284000 | F5: ='12_DevOps_View'!$F$3 -> 344000 | G5: ='12_DevOps_View'!$G$3 -> 442000
A6: Conservative | B6: Consolidated contribution before blocked items | C6: ='14_Consolidated_View'!$C$3 -> -43880.16 | D6: ='14_Consolidated_View'!$D$3 -> -94560.72 | E6: ='14_Consolidated_View'!$E$3 -> -169191.68 | F6: ='14_Consolidated_View'!$F$3 -> -241042.88 | G6: ='14_Consolidated_View'!$G$3 -> -315673.84
A7: Conservative | B7: Discount rate | C7: Blocked - FIN-001 not canonicalized | D7: Blocked - FIN-001 not canonicalized | E7: Blocked - FIN-001 not canonicalized | F7: Blocked - FIN-001 not canonicalized | G7: Blocked - FIN-001 not canonicalized
A8: Conservative | B8: NPV | C8: Blocked - cash-flow timing, discount rate, tax, RB-002, royalty, and NetBank prerequisites unresolved | D8: Blocked - cash-flow timing, discount rate, tax, RB-002, royalty, and NetBank prerequisites unresolved | E8: Blocked - cash-flow timing, discount rate, tax, RB-002, royalty, and NetBank prerequisites unresolved | F8: Blocked - cash-flow timing, discount rate, tax, RB-002, royalty, and NetBank prerequisites unresolved | G8: Blocked - cash-flow timing, discount rate, tax, RB-002, royalty, and NetBank prerequisites unresolved
A9: Conservative | B9: IRR | C9: Blocked - valid investment cash-flow sign pattern is not governed | D9: Blocked - valid investment cash-flow sign pattern is not governed | E9: Blocked - valid investment cash-flow sign pattern is not governed | F9: Blocked - valid investment cash-flow sign pattern is not governed | G9: Blocked - valid investment cash-flow sign pattern is not governed
A10: Conservative | B10: Simple payback | C10: Blocked - beginning investment and true cash-flow basis unavailable | D10: Blocked - beginning investment and true cash-flow basis unavailable | E10: Blocked - beginning investment and true cash-flow basis unavailable | F10: Blocked - beginning investment and true cash-flow basis unavailable | G10: Blocked - beginning investment and true cash-flow basis unavailable
A11: Base | B11: Rural Bank modernization investment cash outflow before timing | C11: ='09_Operating_Expenses'!$C$20 -> 520000 | D11: ='09_Operating_Expenses'!$D$20 -> 1358000 | E11: ='09_Operating_Expenses'!$E$20 -> 2416000 | F11: ='09_Operating_Expenses'!$F$20 -> 4064000 | G11: ='09_Operating_Expenses'!$G$20 -> 6260000
A12: Base | B12: Rural Bank incremental cash contribution before RB-002 | C12: ='10_Rural_Bank_View'!$C$7 -> 51955.68 | D12: ='10_Rural_Bank_View'!$D$7 -> 139087.87 | E12: ='10_Rural_Bank_View'!$E$7 -> 249951.74 | F12: ='10_Rural_Bank_View'!$F$7 -> 422390.98 | G12: ='10_Rural_Bank_View'!$G$7 -> 653667.84
A13: Base | B13: ODTI program contribution before blocked items | C13: ='11_ODTI_View'!$C$6 -> 269371.36 | D13: ='11_ODTI_View'!$D$6 -> 514999.74 | E13: ='11_ODTI_View'!$E$6 -> 777663.49 | F13: ='11_ODTI_View'!$F$6 -> 1200565.9 | G13: ='11_ODTI_View'!$G$6 -> 1681175.7
A14: Base | B14: DevOps contribution before blocked items | C14: ='12_DevOps_View'!$C$5 -> 310000 | D14: ='12_DevOps_View'!$D$5 -> 574000 | E14: ='12_DevOps_View'!$E$5 -> 848000 | F14: ='12_DevOps_View'!$F$5 -> 1292000 | G14: ='12_DevOps_View'!$G$5 -> 1780000
A15: Base | B15: Consolidated contribution before blocked items | C15: ='14_Consolidated_View'!$C$7 -> -3672.96 | D15: ='14_Consolidated_View'!$D$7 -> 24087.62 | E15: ='14_Consolidated_View'!$E$7 -> 67615.23 | F15: ='14_Consolidated_View'!$F$7 -> 132956.93 | G15: ='14_Consolidated_View'!$G$7 -> 234843.52
A16: Base | B16: Discount rate | C16: Blocked - FIN-001 not canonicalized | D16: Blocked - FIN-001 not canonicalized | E16: Blocked - FIN-001 not canonicalized | F16: Blocked - FIN-001 not canonicalized | G16: Blocked - FIN-001 not canonicalized
A17: Base | B17: NPV | C17: Blocked - cash-flow timing, discount rate, tax, RB-002, royalty, and NetBank prerequisites unresolved | D17: Blocked - cash-flow timing, discount rate, tax, RB-002, royalty, and NetBank prerequisites unresolved | E17: Blocked - cash-flow timing, discount rate, tax, RB-002, royalty, and NetBank prerequisites unresolved | F17: Blocked - cash-flow timing, discount rate, tax, RB-002, royalty, and NetBank prerequisites unresolved | G17: Blocked - cash-flow timing, discount rate, tax, RB-002, royalty, and NetBank prerequisites unresolved
A18: Base | B18: IRR | C18: Blocked - valid investment cash-flow sign pattern is not governed | D18: Blocked - valid investment cash-flow sign pattern is not governed | E18: Blocked - valid investment cash-flow sign pattern is not governed | F18: Blocked - valid investment cash-flow sign pattern is not governed | G18: Blocked - valid investment cash-flow sign pattern is not governed
A19: Base | B19: Simple payback | C19: Blocked - beginning investment and true cash-flow basis unavailable | D19: Blocked - beginning investment and true cash-flow basis unavailable | E19: Blocked - beginning investment and true cash-flow basis unavailable | F19: Blocked - beginning investment and true cash-flow basis unavailable | G19: Blocked - beginning investment and true cash-flow basis unavailable
A20: Accelerated | B20: Rural Bank modernization investment cash outflow before timing | C20: ='09_Operating_Expenses'!$C$30 -> 1235000 | D20: ='09_Operating_Expenses'!$D$30 -> 2840000 | E20: ='09_Operating_Expenses'!$E$30 -> 5160000 | F20: ='09_Operating_Expenses'!$F$30 -> 8250000 | G20: ='09_Operating_Expenses'!$G$30 -> 11500000
A21: Accelerated | B21: Rural Bank incremental cash contribution before RB-002 | C21: ='10_Rural_Bank_View'!$C$10 -> 323513.31 | D21: ='10_Rural_Bank_View'!$D$10 -> 766448.18 | E21: ='10_Rural_Bank_View'!$E$10 -> 1406479.9 | F21: ='10_Rural_Bank_View'!$F$10 -> 2260973.1 | G21: ='10_Rural_Bank_View'!$G$10 -> 3162075.8
A22: Accelerated | B22: ODTI program contribution before blocked items | C22: ='11_ODTI_View'!$C$9 -> 850014.39 | D22: ='11_ODTI_View'!$D$9 -> 1559179.1 | E22: ='11_ODTI_View'!$E$9 -> 2588186.3 | F22: ='11_ODTI_View'!$F$9 -> 3922903.9 | G22: ='11_ODTI_View'!$G$9 -> 5285177
A23: Accelerated | B23: DevOps contribution before blocked items | C23: ='12_DevOps_View'!$C$7 -> 710000 | D23: ='12_DevOps_View'!$D$7 -> 1240000 | E23: ='12_DevOps_View'!$E$7 -> 2010000 | F23: ='12_DevOps_View'!$F$7 -> 3000000 | G23: ='12_DevOps_View'!$G$7 -> 4000000
A24: Accelerated | B24: Consolidated contribution before blocked items | C24: ='14_Consolidated_View'!$C$11 -> 463527.7 | D24: ='14_Consolidated_View'!$D$11 -> 1085627.3 | E24: ='14_Consolidated_View'!$E$11 -> 1984666.2 | F24: ='14_Consolidated_View'!$F$11 -> 3183877 | G24: ='14_Consolidated_View'!$G$11 -> 4447252.8
A25: Accelerated | B25: Discount rate | C25: Blocked - FIN-001 not canonicalized | D25: Blocked - FIN-001 not canonicalized | E25: Blocked - FIN-001 not canonicalized | F25: Blocked - FIN-001 not canonicalized | G25: Blocked - FIN-001 not canonicalized
A26: Accelerated | B26: NPV | C26: Blocked - cash-flow timing, discount rate, tax, RB-002, royalty, and NetBank prerequisites unresolved | D26: Blocked - cash-flow timing, discount rate, tax, RB-002, royalty, and NetBank prerequisites unresolved | E26: Blocked - cash-flow timing, discount rate, tax, RB-002, royalty, and NetBank prerequisites unresolved | F26: Blocked - cash-flow timing, discount rate, tax, RB-002, royalty, and NetBank prerequisites unresolved | G26: Blocked - cash-flow timing, discount rate, tax, RB-002, royalty, and NetBank prerequisites unresolved
A27: Accelerated | B27: IRR | C27: Blocked - valid investment cash-flow sign pattern is not governed | D27: Blocked - valid investment cash-flow sign pattern is not governed | E27: Blocked - valid investment cash-flow sign pattern is not governed | F27: Blocked - valid investment cash-flow sign pattern is not governed | G27: Blocked - valid investment cash-flow sign pattern is not governed
A28: Accelerated | B28: Simple payback | C28: Blocked - beginning investment and true cash-flow basis unavailable | D28: Blocked - beginning investment and true cash-flow basis unavailable | E28: Blocked - beginning investment and true cash-flow basis unavailable | F28: Blocked - beginning investment and true cash-flow basis unavailable | G28: Blocked - beginning investment and true cash-flow basis unavailable

Sheet 18_Sensitivity
A1: Sensitivity test | B1: Row driver | C1: Column driver | D1: Target output | E1: Current selected-scenario reference | F1: Status | G1: Notes
A2: Active banks versus employers per bank | B2: ADP-002 active banks | C2: CUS-001 payroll customers per active bank | D2: Year 5 consolidated contribution before blocked items | E2: =CHOOSE(MATCH('01_Control'!$B$2,{"Conservative","Base","Accelerated"},0),'14_Consolidated_View'!$G$3,'14_Consolidated_View'!$G$7,'14_Consolidated_View'!$G$11) -> 234843.52 | F2: Ready as formula target | G2: Two-way grid remains a later implementation; this row locks the target output.
A3: Employer monthly fee versus employer count | B3: EMP-002 employer monthly payroll-service fee | C3: Active employers | D3: Year 5 consolidated core external revenue | E3: =CHOOSE(MATCH('01_Control'!$B$2,{"Conservative","Base","Accelerated"},0),'14_Consolidated_View'!$G$2,'14_Consolidated_View'!$G$6,'14_Consolidated_View'!$G$10) -> 1209024 | F3: Ready as formula target | G3: Sensitivity must recalculate from assumptions, not paste static outputs.
A4: Recipient fee versus transaction volume | B4: PRC-001 recipient disbursement fee | C4: Annual successful payroll transactions | D4: Year 5 ODTI contribution before blocked items | E4: =CHOOSE(MATCH('01_Control'!$B$2,{"Conservative","Base","Accelerated"},0),'11_ODTI_View'!$G$3,'11_ODTI_View'!$G$6,'11_ODTI_View'!$G$9) -> 1681175.7 | F4: Ready as formula target | G4: Transaction-fee sensitivity remains secondary to employer recurring fee sensitivity.
A5: Rural Bank retained amount versus volume | B5: RB-001 retained transaction amount | C5: Annual successful payroll transactions | D5: Year 5 Rural Bank Contribution Before Internal Bank Payroll-Support Cost | E5: =CHOOSE(MATCH('01_Control'!$B$2,{"Conservative","Base","Accelerated"},0),'10_Rural_Bank_View'!$G$4,'10_Rural_Bank_View'!$G$7,'10_Rural_Bank_View'!$G$10) -> 653667.84 | F5: Qualified | G5: True bank contribution remains blocked by RB-002.
A6: ODTI support cost versus active banks | B6: ODTI-001 support cost | C6: ADP-002 active banks | D6: Year 5 ODTI contribution before blocked items | E6: =CHOOSE(MATCH('01_Control'!$B$2,{"Conservative","Base","Accelerated"},0),'11_ODTI_View'!$G$3,'11_ODTI_View'!$G$6,'11_ODTI_View'!$G$9) -> 1681175.7 | F6: Ready as formula target | G6: Pre-tax, pre-royalty, NetBank-fee-blocked.
A7: DevOps cost versus bank count | B7: OPS-003 direct DevOps cost | C7: ADP-002 active banks | D7: Year 5 DevOps contribution | E7: =CHOOSE(MATCH('01_Control'!$B$2,{"Conservative","Base","Accelerated"},0),'12_DevOps_View'!$G$3,'12_DevOps_View'!$G$5,'12_DevOps_View'!$G$7) -> 1780000 | F7: Ready as formula target | G7: Cloud remains outside DevOps under the Level 1 boundary.
A8: Discount rate versus NPV | B8: FIN-001 discount rate | C8: Investment cash flow | D8: NPV | E8: Blocked | F8: Blocked | G8: FIN-001 and valid cash-flow basis are missing.
A9: Shared modernization allocation versus Rural Bank contribution | B9: ALLOC-001 payroll share | C9: Shared modernization cost | D9: Full-cost stress-test result | E9: Blocked | F9: Blocked | G9: Shared allocation remains deferred until additional offerings are modeled.

Sheet 19_Scenarios
A1: Metric | B1: Conservative Year 1 | C1: Conservative Year 5 | D1: Base Year 1 | E1: Base Year 5 | F1: Accelerated Year 1 | G1: Accelerated Year 5 | H1: Source / notes
A2: Active banks | B2: ='04_Adoption'!$C$4 -> 1 | C2: ='04_Adoption'!$G$4 -> 12 | D2: ='04_Adoption'!$C$10 -> 3 | E2: ='04_Adoption'!$G$10 -> 32 | F2: ='04_Adoption'!$C$16 -> 7 | G2: ='04_Adoption'!$G$16 -> 60 | H2: ADP-002.
A3: Active employers | B3: ='04_Adoption'!$C$6 -> 2 | C3: ='04_Adoption'!$G$6 -> 24 | D3: ='04_Adoption'!$C$12 -> 12 | E3: ='04_Adoption'!$G$12 -> 128 | F3: ='04_Adoption'!$C$18 -> 42 | G3: ='04_Adoption'!$G$18 -> 360 | H3: ADP-002 x CUS-001.
A4: Annual successful payroll transactions | B4: ='05_Payroll_Activity'!$C$3 -> 147.2 | C4: ='05_Payroll_Activity'!$G$3 -> 3532.8 | D4: ='05_Payroll_Activity'!$C$6 -> 4032 | E4: ='05_Payroll_Activity'!$G$6 -> 86016 | F4: ='05_Payroll_Activity'!$C$9 -> 29635.2 | G4: ='05_Payroll_Activity'!$G$9 -> 423360 | H4: ADP-002 x ADP-003 x derived VOL-001.
A5: Consolidated Core External Revenue | B5: ='14_Consolidated_View'!$C$2 -> 8547.2 | C5: ='14_Consolidated_View'!$G$2 -> 76132.8 | D5: ='14_Consolidated_View'!$C$6 -> 111048 | E5: ='14_Consolidated_View'!$G$6 -> 1209024 | F5: ='14_Consolidated_View'!$C$10 -> 674270.4 | G5: ='14_Consolidated_View'!$G$10 -> 5946720 | H5: External employer commercial fees counted once.
A6: Consolidated Core Contribution Before Blocked Items | B6: ='14_Consolidated_View'!$C$3 -> -43880.16 | C6: ='14_Consolidated_View'!$G$3 -> -315673.84 | D6: ='14_Consolidated_View'!$C$7 -> -3672.96 | E6: ='14_Consolidated_View'!$G$7 -> 234843.52 | F6: ='14_Consolidated_View'!$C$11 -> 463527.7 | G6: ='14_Consolidated_View'!$G$11 -> 4447252.8 | H6: Pre-tax, pre-royalty, NetBank-fee-blocked.
A7: Rural Bank Contribution Before Internal Bank Payroll-Support Cost | B7: ='10_Rural_Bank_View'!$C$4 -> 3703.94 | C7: ='10_Rural_Bank_View'!$G$4 -> 39874.46 | D7: ='10_Rural_Bank_View'!$C$7 -> 51955.68 | E7: ='10_Rural_Bank_View'!$G$7 -> 653667.84 | F7: ='10_Rural_Bank_View'!$C$10 -> 323513.31 | G7: ='10_Rural_Bank_View'!$G$10 -> 3162075.8 | H7: Qualified by blocked RB-002.
A8: ODTI Pre-Tax/Pre-Royalty/NetBank-Fee-Blocked Contribution | B8: ='11_ODTI_View'!$C$3 -> 72415.9 | C8: ='11_ODTI_View'!$G$3 -> 374451.7 | D8: ='11_ODTI_View'!$C$6 -> 269371.36 | E8: ='11_ODTI_View'!$G$6 -> 1681175.7 | F8: ='11_ODTI_View'!$C$9 -> 850014.39 | G8: ='11_ODTI_View'!$G$9 -> 5285177 | H8: Final ODTI net result blocked.
A9: DevOps Contribution | B9: ='12_DevOps_View'!$C$3 -> 108000 | C9: ='12_DevOps_View'!$G$3 -> 442000 | D9: ='12_DevOps_View'!$C$5 -> 310000 | E9: ='12_DevOps_View'!$G$5 -> 1780000 | F9: ='12_DevOps_View'!$C$7 -> 710000 | G9: ='12_DevOps_View'!$G$7 -> 4000000 | H9: Cloud remains outside DevOps.
A10: Optional SMS Increment | B10: ='13_SMS_Variant'!$C$6 -> 8.28 | C10: ='13_SMS_Variant'!$G$6 -> 198.72 | D10: ='13_SMS_Variant'!$C$11 -> 919.3 | E10: ='13_SMS_Variant'!$G$11 -> 19611.65 | F10: ='13_SMS_Variant'!$C$16 -> 11872.16 | G10: ='13_SMS_Variant'!$G$16 -> 169602.25 | H10: Optional enhancement, excluded from Core Payroll headline.
A11: NPV / IRR | B11: Blocked | C11: Blocked | D11: Blocked | E11: Blocked | F11: Blocked | G11: Blocked | H11: FIN-001, cash-flow timing, tax, RB-002, royalty, and NetBank prerequisites unresolved.

Sheet 20_Dashboard
A1: Dashboard item | B1: Selected scenario value | C1: Source | D1: Status | E1: Notes
A2: Selected scenario | B2: ='01_Control'!$B$2 -> Base | C2: 01_Control | D2: OK | E2: Controlled scenario selector.
A3: Active banks - Year 5 | B3: =CHOOSE(MATCH('01_Control'!$B$2,{"Conservative","Base","Accelerated"},0),'04_Adoption'!$G$4,'04_Adoption'!$G$10,'04_Adoption'!$G$16) -> 32 | C3: 04_Adoption / ADP-002 | D3: OK | E3: Scenario-selected active banks.
A4: Active employers - Year 5 | B4: =CHOOSE(MATCH('01_Control'!$B$2,{"Conservative","Base","Accelerated"},0),'04_Adoption'!$G$6,'04_Adoption'!$G$12,'04_Adoption'!$G$18) -> 128 | C4: 04_Adoption / CUS-001 | D4: OK | E4: Active employers drive recurring service fees.
A5: Annual successful payroll transactions - Year 5 | B5: =CHOOSE(MATCH('01_Control'!$B$2,{"Conservative","Base","Accelerated"},0),'05_Payroll_Activity'!$G$3,'05_Payroll_Activity'!$G$6,'05_Payroll_Activity'!$G$9) -> 86016 | C5: 05_Payroll_Activity / VOL-001 | D5: OK | E5: Component-derived volume.
A6: Consolidated Core External Revenue - Year 5 | B6: =CHOOSE(MATCH('01_Control'!$B$2,{"Conservative","Base","Accelerated"},0),'14_Consolidated_View'!$G$2,'14_Consolidated_View'!$G$6,'14_Consolidated_View'!$G$10) -> 1209024 | C6: 14_Consolidated_View | D6: OK | E6: External customer inflows counted once.
A7: Consolidated Core Contribution Before Blocked Items - Year 5 | B7: =CHOOSE(MATCH('01_Control'!$B$2,{"Conservative","Base","Accelerated"},0),'14_Consolidated_View'!$G$3,'14_Consolidated_View'!$G$7,'14_Consolidated_View'!$G$11) -> 234843.52 | C7: 14_Consolidated_View | D7: OK | E7: Pre-tax, pre-royalty, NetBank-fee-blocked.
A8: Rural Bank Contribution Before Internal Bank Payroll-Support Cost - Year 5 | B8: =CHOOSE(MATCH('01_Control'!$B$2,{"Conservative","Base","Accelerated"},0),'10_Rural_Bank_View'!$G$4,'10_Rural_Bank_View'!$G$7,'10_Rural_Bank_View'!$G$10) -> 653667.84 | C8: 10_Rural_Bank_View / RB-002 | D8: Qualified | E8: True bank contribution remains blocked by RB-002.
A9: ODTI Contribution - Year 5 | B9: =CHOOSE(MATCH('01_Control'!$B$2,{"Conservative","Base","Accelerated"},0),'11_ODTI_View'!$G$3,'11_ODTI_View'!$G$6,'11_ODTI_View'!$G$9) -> 1681175.7 | C9: 11_ODTI_View | D9: Qualified | E9: Pre-tax, pre-royalty, NetBank-fee-blocked.
A10: DevOps Contribution - Year 5 | B10: =CHOOSE(MATCH('01_Control'!$B$2,{"Conservative","Base","Accelerated"},0),'12_DevOps_View'!$G$3,'12_DevOps_View'!$G$5,'12_DevOps_View'!$G$7) -> 1780000 | C10: 12_DevOps_View | D10: OK | E10: Direct recurring cost only; cloud remains outside DevOps.
A11: Optional SMS Increment - Year 5 | B11: =CHOOSE(MATCH('01_Control'!$B$2,{"Conservative","Base","Accelerated"},0),'13_SMS_Variant'!$G$6,'13_SMS_Variant'!$G$11,'13_SMS_Variant'!$G$16) -> 19611.65 | C11: 13_SMS_Variant | D11: Optional | E11: SMS is not part of Core Payroll headline.
A12: Full-Cost Stand-Alone Stress Result - Year 5 | B12: =CHOOSE(MATCH('01_Control'!$B$2,{"Conservative","Base","Accelerated"},0),'14_Consolidated_View'!$G$3,'14_Consolidated_View'!$G$7,'14_Consolidated_View'!$G$11)-CHOOSE(MATCH('01_Control'!$B$2,{"Conservative","Base","Accelerated"},0),'09_Operating_Expenses'!$G$10,'09_Operating_Expenses'!$G$20,'09_Operating_Expenses'!$G$30) -> -6025156.5 | C12: 14_Consolidated_View less 09_Operating_Expenses | D12: Stress test | E12: Payroll alone remains a stress-test view, not the primary operating view.
A13: Blocked-input count | B13: 11 | C13: 02_Assumptions / blocked input register | D13: Blocked visible | E13: Blocked items are visible rather than treated as zero.
A14: ERROR count | B14: =COUNTIF('21_Checks'!$E$2:$E$200,"ERROR") -> 0 | C14: 21_Checks | D14: OK | E14: Dashboard surfaces model check failures.
A15: NPV / IRR | B15: Blocked | C15: 17_Capital_Budgeting | D15: Blocked | E15: FIN-001 and valid cash-flow series are unavailable.

Sheet 22_Source_Lineage
A1: Workbook item | B1: Assumption IDs | C1: Source document | D1: Workbook sheets | E1: Provisional input IDs / decisions | F1: Status
A2: Adoption and activation | B2: ADP-001; ADP-002; ADP-003 | C2: docs/economics/offerings/rural-bank-payroll-starter/provisional-input-register-level-1.md | D2: 02_Assumptions; 04_Adoption; 19_Scenarios; 20_Dashboard | E2: PI-L1-001; PI-L1-002; PI-L1-003 | F2: Provisional
A3: Payroll activity | B3: CUS-001; CUS-002; CUS-003; VOL-002; VOL-001 | C3: docs/economics/offerings/rural-bank-payroll-starter/provisional-input-register-level-1.md | D3: 05_Payroll_Activity; 19_Scenarios | E3: PI-L1-004 through PI-L1-008 | F3: Derived and provisional
A4: Pricing and employer fees | B4: EMP-001; EMP-002; PRC-001; RB-001 | C4: docs/economics/offerings/rural-bank-payroll-starter/provisional-input-register-level-1.md | D4: 06_Pricing; 07_Revenue | E4: PI-L1-009; PI-L1-010; PI-L1-013; PI-L1-014 | F4: Provisional
A5: Stakeholder revenue splits | B5: Decision 0003 | C5: docs/decisions/0003-payroll-starter-economic-treatment.md | D5: 06_Pricing; 10_Rural_Bank_View; 11_ODTI_View | E5: PI-L1-015; PI-L1-016 | F5: Decision-backed provisional
A6: Rural Bank contribution | B6: RB-001; RB-002; RISK-002 | C6: docs/economics/offerings/rural-bank-payroll-starter/offering-economics-level-1.md | D6: 10_Rural_Bank_View; 15_Profit_and_Loss; 20_Dashboard | E6: PI-L1-014; RB-002 blocked; PI-L1-023 | F6: Qualified / blocked
A7: ODTI contribution | B7: LIC-004; LIC-005; ODTI-001; ODTI-002; TAX-001; ROY-001; NET-001 | C7: docs/economics/offerings/rural-bank-payroll-starter/offering-economics-level-1.md | D7: 11_ODTI_View; 15_Profit_and_Loss | E7: PI-L1-011; PI-L1-012; PI-L1-017; PI-L1-018 | F7: Qualified / blocked
A8: DevOps economics | B8: OPS-001; OPS-002; OPS-003; CLD-001 | C8: docs/economics/offerings/rural-bank-payroll-starter/offering-economics-level-1.md | D8: 12_DevOps_View; 09_Operating_Expenses | E8: PI-L1-019; PI-L1-020; PI-L1-021; PI-L1-022 | F8: Provisional
A9: Optional SMS economics | B9: ATT-001; VAS-001; CST-001; SMS-001; SMS-002; SMS-003; SMS-004 | C9: docs/economics/offerings/rural-bank-payroll-starter/offering-economics-level-1.md | D9: 13_SMS_Variant | E9: PI-L1-024 through PI-L1-030 | F9: Optional / partially blocked
A10: Consolidated external revenue | B10: EMP-001; EMP-002; PRC-001; RISK-002 | C10: docs/economics/offerings/rural-bank-payroll-starter/five-year-revenue-projection-summary.md | D10: 14_Consolidated_View; 19_Scenarios; 20_Dashboard | E10: PI-L1-009; PI-L1-010; PI-L1-013; PI-L1-023 | F10: Provisional
A11: Cost classification | B11: CST-001; CLD-001; NET-001; TAX-001 | C11: docs/economics/offerings/rural-bank-payroll-starter/spreadsheet-financial-model.md | D11: 08_Cost_of_Sales; 09_Operating_Expenses | E11: PI-L1-026; PI-L1-022; NET-001 blocked; TAX-001 blocked | F11: Qualified / blocked
A12: Management P&L | B12: RB-002; TAX-001; ROY-001; NET-001 | C12: docs/economics/offerings/rural-bank-payroll-starter/spreadsheet-financial-model.md | D12: 15_Profit_and_Loss | E12: Blocked exclusions | F12: Management view only
... A16: Blocked assumptions and exclusions | B16: TAX-001; ROY-001; NET-001; NET-002; PAR-001; RB-002; SMS-002; BAT-001; ALLOC-001; ALLOC-002; PLT-001 | C16: docs/economics/offerings/rural-bank-payroll-starter/provisional-input-register-level-1.md | D16: 02_Assumptions; 21_Checks; 22_Source_Lineage | E16: Blocked/excluded rows | F16: Blocked or excluded
